Workbook

Sheet Language Rules Can Change
B1: 1 | C1: 2 | D1: 3 | E1: 4 | F1: 5 | G1: 6 | H1: 7 | I1: 8 | J1: 9 | K1: 10 | L1: 11 | M1: 12 | N1: 13 | O1: 14 | P1: 15 | Q1: 16 | R1: 17 | S1: 18 | T1: 19 | U1: 20 | V1: 21 | W1: 22 | X1: 23 | Y1: 24 | Z1: 25 | AA1: 26 | AB1: 27 | AC1: 28 | AD1: 29 | AE1: 30 | AF1: 31 | AG1: 32 | AH1: 33 | AI1: 34 | AJ1: 35 | AK1: 36 | AL1: 37 | AM1: 38 | AN1: 39 | AO1: 40 | AP1: 41 | AQ1: 42 | AR1: 43 | AS1: 44 | AT1: 45 | AU1: 46
A2: conversion chart final | B2: p | C2: b | D2: m | E2: w | F2: f | G2: v | H2: θ | I2: ð | J2: t | K2: s | L2: ʧ | M2: d | N2: n | O2: z | P2: ʤ | Q2: r | R2: l | S2: ʃ | T2: ʒ | U2: jə | V2: k | W2: g | X2: ŋ | Y2: h | Z2: " | AA2: æ | AB2: ɛ | AC2: ɪ | AD2: ɒ | AE2: ʌ | AF2: ʊ | AG2: eɪ | AH2: i | AI2: aɪ | AJ2: əʊ | AK2: u | AL2: ɑ | AM2: ɜ | AN2: ɔ | AO2: ju | AP2: ɔɪ | AQ2: aʊ | AR2: ə | AS2: e | AT2: ɪə | AU2: jʊə
A3: p | B3: 0.0015419035 | C3: 0.035034373 | D3: 0.057341469 | E3: 0.064843068 | F3: 0.095841208 | G3: 0.11749202 | H3: 0.1268785 | I3: 0.14513825 | J3: 0.16108627 | K3: 0.19890827 | L3: 0.21082051 | M3: 0.21825954 | N3: 0.2302602 | O3: 0.23163407 | P3: 0.23938983 | Q3: 0.24525798 | R3: 0.24650522 | S3: 0.26557425 | T3: 0.26903654 | U3: 0.26911709 | V3: 0.2881153 | W3: 0.29390286 | X3: 0.29956027 | Y3: 0.30060715 | Z3: 1 | AA3: 1 | AB3: 1 | AC3: 1 | AD3: 1 | AE3: 1 | AF3: 1 | AG3: 1 | AH3: 1 | AI3: 1 | AJ3: 1 | AK3: 1 | AL3: 1 | AM3: 1 | AN3: 1 | AO3: 1 | AP3: 1 | AQ3: 1 | AR3: 1 | AS3: 1 | AT3: 1 | AU3: 1
A4: b | B4: 0.0010498906 | C4: 0.041592481 | D4: 0.068715739 | E4: 0.077796415 | F4: 0.11473332 | G4: 0.1409416 | H4: 0.15230393 | I4: 0.17525746 | J4: 0.19456252 | K4: 0.24210689 | L4: 0.25616615 | M4: 0.26551744 | N4: 0.27968106 | O4: 0.28124017 | P4: 0.29062852 | Q4: 0.29861982 | R4: 0.3001296 | S4: 0.32321265 | T4: 0.32792762 | U4: 0.32807388 | V4: 0.35107119 | W4: 0.35895276 | X4: 0.36408897 | Y4: 0.36503941 | Z4: 1 | AA4: 1 | AB4: 1 | AC4: 1 | AD4: 1 | AE4: 1 | AF4: 1 | AG4: 1 | AH4: 1 | AI4: 1 | AJ4: 1 | AK4: 1 | AL4: 1 | AM4: 1 | AN4: 1 | AO4: 1 | AP4: 1 | AQ4: 1 | AR4: 1 | AS4: 1 | AT4: 1 | AU4: 1
A5: m | B5: 0.00075365178 | C5: 0.029986605 | D5: 0.06475467 | E5: 0.076212897 | F5: 0.12356063 | G5: 0.1566309 | H5: 0.17119575 | I5: 0.20061883 | J5: 0.21453861 | K5: 0.26024733 | L5: 0.27376377 | M5: 0.28025672 | N5: 0.29911071 | O5: 0.30105931 | P5: 0.31234164 | Q5: 0.32258533 | R5: 0.32476257 | S5: 0.35250235 | T5: 0.35854626 | U5: 0.35868687 | V5: 0.37526892 | W5: 0.38032043 | X5: 0.3877273 | Y5: 0.38955477 | Z5: 1 | AA5: 1 | AB5: 1 | AC5: 1 | AD5: 1 | AE5: 1 | AF5: 1 | AG5: 1 | AH5: 1 | AI5: 1 | AJ5: 1 | AK5: 1 | AL5: 1 | AM5: 1 | AN5: 1 | AO5: 1 | AP5: 1 | AQ5: 1 | AR5: 1 | AS5: 1 | AT5: 1 | AU5: 1
A6: w | B6: 0.00035469368 | C6: 0.01405155 | D6: 0.030087302 | E6: 0.060046322 | F6: 0.099042313 | G6: 0.1267116 | H6: 0.13870733 | I6: 0.16294042 | J6: 0.16973417 | K6: 0.20598596 | L6: 0.22653781 | M6: 0.22982868 | N6: 0.23903063 | O6: 0.24067667 | P6: 0.25678319 | Q6: 0.28209354 | R6: 0.28727388 | S6: 0.31164371 | T6: 0.31662152 | U6: 0.31708475 | V6: 0.32315458 | W6: 0.32592823 | X6: 0.3286395 | Y6: 0.32964292 | Z6: 1 | AA6: 1 | AB6: 1 | AC6: 1 | AD6: 1 | AE6: 1 | AF6: 1 | AG6: 1 | AH6: 1 | AI6: 1 | AJ6: 1 | AK6: 1 | AL6: 1 | AM6: 1 | AN6: 1 | AO6: 1 | AP6: 1 | AQ6: 1 | AR6: 1 | AS6: 1 | AT6: 1 | AU6: 1
A7: f | B7: 0.00037118235 | C7: 0.014480803 | D7: 0.031262011 | E7: 0.041137805 | F7: 0.11401066 | G7: 0.16490909 | H7: 0.1868775 | I7: 0.23125684 | J7: 0.24325423 | K7: 0.31329183 | L7: 0.33479908 | M7: 0.34039532 | N7: 0.35664549 | O7: 0.35974609 | P7: 0.37724963 | Q7: 0.39159674 | R7: 0.39472432 | S7: 0.43776015 | T7: 0.44622513 | U7: 0.44646752 | V7: 0.46075951 | W7: 0.46511339 | X7: 0.47149733 | Y7: 0.47385997 | Z7: 1 | AA7: 1 | AB7: 1 | AC7: 1 | AD7: 1 | AE7: 1 | AF7: 1 | AG7: 1 | AH7: 1 | AI7: 1 | AJ7: 1 | AK7: 1 | AL7: 1 | AM7: 1 | AN7: 1 | AO7: 1 | AP7: 1 | AQ7: 1 | AR7: 1 | AS7: 1 | AT7: 1 | AU7: 1
A8: v | B8: 0.00025350148 | C8: 0.010042718 | D8: 0.021503557 | E8: 0.033494206 | F8: 0.083263214 | G8: 0.1450613 | H8: 0.17185322 | I8: 0.22573618 | J8: 0.24030276 | K8: 0.32400989 | L8: 0.35012281 | M8: 0.3571788 | N8: 0.37690886 | O8: 0.38067344 | P8: 0.40192529 | Q8: 0.42001473 | R8: 0.42371715 | S8: 0.47596889 | T8: 0.48664191 | U8: 0.48697298 | V8: 0.50432554 | W8: 0.51027256 | X8: 0.51802359 | Y8: 0.52089218 | Z8: 1 | AA8: 1 | AB8: 1 | AC8: 1 | AD8: 1 | AE8: 1 | AF8: 1 | AG8: 1 | AH8: 1 | AI8: 1 | AJ8: 1 | AK8: 1 | AL8: 1 | AM8: 1 | AN8: 1 | AO8: 1 | AP8: 1 | AQ8: 1 | AR8: 1 | AS8: 1 | AT8: 1 | AU8: 1
A9: θ | B9: 0.00023262531 | C9: 0.0069699222 | D9: 0.014982893 | E9: 0.019698551 | F9: 0.053799167 | G9: 0.096330866 | H9: 0.12911163 | I9: 0.19533345 | J9: 0.21315613 | K9: 0.31557445 | L9: 0.34702522 | M9: 0.35565845 | N9: 0.3797988 | O9: 0.38433291 | P9: 0.41033522 | Q9: 0.43246823 | R9: 0.43717248 | S9: 0.50110414 | T9: 0.51416292 | U9: 0.51456799 | V9: 0.53845333 | W9: 0.54572969 | X9: 0.55639878 | Y9: 0.56034732 | Z9: 1 | AA9: 1 | AB9: 1 | AC9: 1 | AD9: 1 | AE9: 1 | AF9: 1 | AG9: 1 | AH9: 1 | AI9: 1 | AJ9: 1 | AK9: 1 | AL9: 1 | AM9: 1 | AN9: 1 | AO9: 1 | AP9: 1 | AQ9: 1 | AR9: 1 | AS9: 1 | AT9: 1 | AU9: 1
A10: ð | B10: 0.00027930349 | C10: 0.0048294733 | D10: 0.010241195 | E10: 0.013426011 | F10: 0.036456551 | G10: 0.06505353 | H10: 0.087192681 | I10: 0.16670246 | J10: 0.18776704 | K10: 0.31128541 | L10: 0.34904704 | M10: 0.35941259 | N10: 0.38794403 | O10: 0.39338794 | P10: 0.42412001 | Q10: 0.45069419 | R10: 0.45634239 | S10: 0.53190309 | T10: 0.54758221 | U10: 0.54803818 | V10: 0.5767163 | W10: 0.58654477 | X10: 0.59935471 | Y10: 0.60409555 | Z10: 1 | AA10: 1 | AB10: 1 | AC10: 1 | AD10: 1 | AE10: 1 | AF10: 1 | AG10: 1 | AH10: 1 | AI10: 1 | AJ10: 1 | AK10: 1 | AL10: 1 | AM10: 1 | AN10: 1 | AO10: 1 | AP10: 1 | AQ10: 1 | AR10: 1 | AS10: 1 | AT10: 1 | AU10: 1
A11: t | B11: 0.00022466324 | C11: 0.0067313625 | D11: 0.011084387 | E11: 0.012602472 | F11: 0.023188225 | G11: 0.036332534 | H11: 0.046463342 | I11: 0.082278282 | J11: 0.13606783 | K11: 0.23498068 | L11: 0.26535498 | M11: 0.29141041 | N11: 0.33221009 | O11: 0.33658901 | P11: 0.36170133 | Q11: 0.3830768 | R11: 0.38762004 | S11: 0.44936351 | T11: 0.46197532 | U11: 0.46236653 | V11: 0.53156996 | W11: 0.55440873 | X11: 0.57158193 | Y11: 0.57539532 | Z11: 1 | AA11: 1 | AB11: 1 | AC11: 1 | AD11: 1 | AE11: 1 | AF11: 1 | AG11: 1 | AH11: 1 | AI11: 1 | AJ11: 1 | AK11: 1 | AL11: 1 | AM11: 1 | AN11: 1 | AO11: 1 | AP11: 1 | AQ11: 1 | AR11: 1 | AS11: 1 | AT11: 1 | AU11: 1
A12: s | B12: 0.00025374279 | C12: 0.0043874998 | D12: 0.0080748472 | E12: 0.010164492 | F12: 0.026105735 | G12: 0.04559066 | H12: 0.060608417 | I12: 0.11478345 | J12: 0.14029923 | K12: 0.28991853 | L12: 0.33586385 | M12: 0.34822358 | N12: 0.38278406 | O12: 0.38940778 | P12: 0.42663391 | Q12: 0.45832058 | R12: 0.46516231 | S12: 0.5566899 | T12: 0.57538546 | U12: 0.57592397 | V12: 0.60849099 | W12: 0.62039634 | X12: 0.63494337 | Y12: 0.64032709 | Z12: 1 | AA12: 1 | AB12: 1 | AC12: 1 | AD12: 1 | AE12: 1 | AF12: 1 | AG12: 1 | AH12: 1 | AI12: 1 | AJ12: 1 | AK12: 1 | AL12: 1 | AM12: 1 | AN12: 1 | AO12: 1 | AP12: 1 | AQ12: 1 | AR12: 1 | AS12: 1 | AT12: 1 | AU12: 1
A13: ʧ | B13: 0.00020788062 | C13: 0.003469061 | D13: 0.0063780625 | E13: 0.009538598 | F13: 0.022598576 | G13: 0.038815127 | H13: 0.051118533 | I13: 0.09530456 | J13: 0.11620855 | K13: 0.23878525 | L13: 0.30570265 | M13: 0.31598918 | N13: 0.3443031 | O13: 0.34970551 | P13: 0.40416583 | Q13: 0.4503161 | R13: 0.46012509 | S13: 0.53510974 | T13: 0.55066933 | U13: 0.55148381 | V13: 0.57994329 | W13: 0.58969684 | X13: 0.60240912 | Y13: 0.60711382 | Z13: 1 | AA13: 1 | AB13: 1 | AC13: 1 | AD13: 1 | AE13: 1 | AF13: 1 | AG13: 1 | AH13: 1 | AI13: 1 | AJ13: 1 | AK13: 1 | AL13: 1 | AM13: 1 | AN13: 1 | AO13: 1 | AP13: 1 | AQ13: 1 | AR13: 1 | AS13: 1 | AT13: 1 | AU13: 1
A14: d | B14: 0.00028895826 | C14: 0.0049964152 | D14: 0.0080290933 | E14: 0.0091273954 | F14: 0.016502309 | G14: 0.026011934 | H14: 0.033341355 | I14: 0.059663985 | J14: 0.098579567 | K14: 0.17014088 | L14: 0.19246485 | M14: 0.22597692 | N14: 0.27868709 | O14: 0.28431918 | P14: 0.31611358 | Q14: 0.34360636 | R14: 0.3494498 | S14: 0.42762242 | T14: 0.44384354 | U14: 0.44445678 | V14: 0.53346511 | W14: 0.56396978 | X14: 0.58550548 | Y14: 0.5904102 | Z14: 1 | AA14: 1 | AB14: 1 | AC14: 1 | AD14: 1 | AE14: 1 | AF14: 1 | AG14: 1 | AH14: 1 | AI14: 1 | AJ14: 1 | AK14: 1 | AL14: 1 | AM14: 1 | AN14: 1 | AO14: 1 | AP14: 1 | AQ14: 1 | AR14: 1 | AS14: 1 | AT14: 1 | AU14: 1
... A47: jʊə | B47: 0 | C47: 0 | D47: 0 | E47: 0 | F47: 0 | G47: 0 | H47: 0 | I47: 0 | J47: 0 | K47: 0 | L47: 0 | M47: 0 | N47: 0 | O47: 0 | P47: 0 | Q47: 0 | R47: 0 | S47: 0 | T47: 0 | U47: 0 | V47: 0 | W47: 0 | X47: 0 | Y47: 0 | Z47: 0.50373807 | AA47: 0.51104529 | AB47: 0.51242131 | AC47: 0.51346775 | AD47: 0.53034804 | AE47: 0.5369792 | AF47: 0.54051852 | AG47: 0.55238271 | AH47: 0.58958317 | AI47: 0.59711602 | AJ47: 0.62392474 | AK47: 0.64468519 | AL47: 0.67640709 | AM47: 0.70842787 | AN47: 0.73930538 | AO47: 0.7755099 | AP47: 0.79923294 | AQ47: 0.88204278 | AR47: 0.88935051 | AS47: 0.95413166 | AT47: 0.99643371 | AU47: 1
A51: Short | B51: æ | C51: ɛ | D51: ɪ | E51: ɒ | F51: ʌ | G51: ʊ
A52: Long | B52: eɪ | C52: i | D52: aɪ | E52: əʊ | G52: u
A53: R | B53: ɑ | C53: ɜ | D53: ɔ
A54: Other | B54: ju | C54: ɔɪ | D54: aʊ | E54: ə | F54: e | G54: ɪə | H54: jʊə
B57: 0.0625 | C57: 0.125 | D57: 0.1875 | E57: 0.25 | F57: 0.3125 | G57: 0.375 | H57: 0.4375 | I57: 0.5 | J57: 0.5625 | K57: 0.625 | L57: 0.6875 | M57: 0.75 | N57: 0.8125 | O57: 0.875 | P57: 0.9375 | Q57: 1 | V57: 0.14285714 | W57: 0.28571429 | X57: 0.42857143 | Y57: 0.57142857 | Z57: 0.71428571 | AA57: 0.85714286 | AB57: 1
B58: 1 | C58: 0.9375 | D58: 0.875 | E58: 0.8125 | F58: 0.75 | G58: 0.6875 | H58: 0.625 | I58: 0.5625 | J58: 0.5 | K58: 0.4375 | L58: 0.375 | M58: 0.3125 | N58: 0.25 | O58: 0.1875 | P58: 0.125 | Q58: 0.0625 | V58: 1 | W58: 0.85714286 | X58: 0.71428571 | Y58: 0.57142857 | Z58: 0.42857143 | AA58: 0.28571429 | AB58: 0.14285714
B59: Bilabial | D59: Labio-dental | F59: Inter-dental | H59: Alveolar | J59: Post-alveolar | L59: Palatal | N59: Velar | P59: Glottal | U59: Short | V59: æ | W59: ɛ | X59: ɪ | Y59: ɒ | Z59: ʌ | AA59: ʊ | AC59: 0.25 | AD59: 1
A60: Stops | B60: p | C60: b | H60: t | I60: d | N60: k | O60: g | R60: 0.16666667 | S60: 1 | U60: Long | V60: eɪ | W60: i | X60: aɪ | Y60: əʊ | AA60: u | AC60: 0.5 | AD60: 0.75
A61: Nasal | C61: m | I61: n | O61: ŋ | R61: 0.33333333 | S61: 0.83333333 | U61: R | V61: ɑ | W61: ɜ | X61: ɔ | AC61: 0.75 | AD61: 0.5
A62: Fricative | D62: f | E62: v | F62: θ | G62: ð | H62: s | I62: z | J62: ʃ | K62: ʒ | P62: h | R62: 0.5 | S62: 0.66666667 | U62: Other | V62: ju | W62: ɔɪ | X62: aʊ | Y62: ə | Z62: e | AA62: ɪə | AB62: jʊə | AC62: 1 | AD62: 0.25
A63: Affricates | H63: ʧ | I63: ʤ | R63: 0.66666667 | S63: 0.5
A64: Approximants | C64: w | I64: r | M64: jə | R64: 0.83333333 | S64: 0.33333333
A65: Lateral | I65: l | R65: 1 | S65: 0.16666667
A68: 1 | B68: 0.0625 | C68: 0.125 | D68: 0.1875 | E68: 0.25 | F68: 0.3125 | G68: 0.375 | H68: 0.4375 | I68: 0.5 | J68: 0.5625 | K68: 0.625 | L68: 0.6875 | M68: 0.75 | N68: 0.8125 | O68: 0.875 | P68: 0.9375 | Q68: 1 | U68: 2 | V68: 0.14285714 | W68: 0.28571429 | X68: 0.42857143 | Y68: 0.57142857 | Z68: 0.71428571 | AA68: 0.85714286 | AB68: 1
A69: 2 | B69: 1 | C69: 0.9375 | D69: 0.875 | E69: 0.8125 | F69: 0.75 | G69: 0.6875 | H69: 0.625 | I69: 0.5625 | J69: 0.5 | K69: 0.4375 | L69: 0.375 | M69: 0.3125 | N69: 0.25 | O69: 0.1875 | P69: 0.125 | Q69: 0.0625 | U69: 1 | V69: 1 | W69: 0.85714286 | X69: 0.71428571 | Y69: 0.57142857 | Z69: 0.42857143 | AA69: 0.28571429 | AB69: 0.14285714
B70: Bilabial | D70: Labio-dental | F70: Inter-dental | H70: Alveolar | J70: Post-alveolar | L70: Palatal | N70: Velar | P70: Glottal | U70: Short | V70: 0.25 | W70: 0.21428571 | X70: 0.17857143 | Y70: 0.14285714 | Z70: 0.10714286 | AA70: 0.071428571 | AC70: 0.25 | AD70: 1
A71: Stops | B71: 0.0625 | C71: 0.125 | H71: 0.4375 | I71: 0.5 | N71: 0.8125 | O71: 0.875 | R71: 0.16666667 | S71: 1 | U71: Long | V71: 0.5 | W71: 0.42857143 | X71: 0.35714286 | Y71: 0.28571429 | AA71: 0.14285714 | AC71: 0.5 | AD71: 0.75
A72: Nasal | C72: 0.10416667 | I72: 0.41666667 | O72: 0.72916667 | R72: 0.33333333 | S72: 0.83333333 | U72: R | V72: 0.75 | W72: 0.64285714 | X72: 0.53571429 | AC72: 0.75 | AD72: 0.5
A73: Fricative | D73: 0.125 | E73: 0.16666667 | F73: 0.20833333 | G73: 0.25 | H73: 0.29166667 | I73: 0.33333333 | J73: 0.375 | K73: 0.41666667 | P73: 0.625 | R73: 0.5 | S73: 0.66666667 | U73: Other | V73: 1 | W73: 0.85714286 | X73: 0.71428571 | Y73: 0.57142857 | Z73: 0.42857143 | AA73: 0.28571429 | AB73: 0.14285714 | AC73: 1 | AD73: 0.25
A74: Affricates | H74: 0.21875 | I74: 0.25 | R74: 0.66666667 | S74: 0.5
A75: Approximants | C75: 0.041666667 | I75: 0.16666667 | M75: 0.25 | R75: 0.83333333 | S75: 0.33333333
A76: Lateral | I76: 0.083333333 | R76: 1 | S76: 0.16666667
A81: 1 | B81: 2 | C81: 3 | D81: 4 | E81: 5 | F81: 6 | G81: 7 | H81: 8 | I81: 9 | J81: 10 | K81: 11 | L81: 12 | M81: 13 | N81: 14 | O81: 15 | P81: 16 | Q81: 17 | R81: 18 | S81: 19 | T81: 20 | U81: 21 | V81: 22 | W81: 23 | X81: 24 | Y81: 25
A82: conversion chart 1 | B82: p | C82: b | D82: m | E82: w | F82: f | G82: v | H82: θ | I82: ð | J82: t | K82: s | L82: ʧ | M82: d | N82: n | O82: z | P82: ʤ | Q82: r | R82: l | S82: ʃ | T82: ʒ | U82: jə | V82: k | W82: g | X82: ŋ | Y82: h | Z82: æ | AA82: ɛ | AB82: ɪ | AC82: ɒ | AD82: ʌ | AE82: ʊ | AF82: eɪ | AG82: i | AH82: aɪ | AI82: əʊ | AJ82: u | AK82: ɑ | AL82: ɜ | AM82: ɔ | AN82: ju | AO82: ɔɪ | AP82: aʊ | AQ82: ə | AR82: e | AS82: ɪə | AT82: jʊə | AU82: 1
A83: p | B83: 0 | C83: 1 | D83: 2 | E83: 5 | F83: 4 | G83: 5 | H83: 6 | I83: 7 | J83: 6 | K83: 7 | L83: 8 | M83: 7 | N83: 8 | O83: 9 | P83: 10 | Q83: 11 | R83: 12 | S83: 10 | T83: 11 | U83: 15 | V83: 12 | W83: 13 | X83: 14 | Y83: 16 | Z83: 100 | AA83: 100 | AB83: 100 | AC83: 100 | AD83: 100 | AE83: 100 | AF83: 100 | AG83: 100 | AH83: 100 | AI83: 100 | AJ83: 100 | AK83: 100 | AL83: 100 | AM83: 100 | AN83: 100 | AO83: 100 | AP83: 100 | AQ83: 100 | AR83: 100 | AS83: 100 | AT83: 100 | AU83: 2
A84: b | B84: 1 | C84: 0 | D84: 1 | E84: 4 | F84: 3 | G84: 4 | H84: 5 | I84: 6 | J84: 5 | K84: 6 | L84: 7 | M84: 6 | N84: 7 | O84: 8 | P84: 9 | Q84: 10 | R84: 11 | S84: 9 | T84: 10 | U84: 14 | V84: 11 | W84: 12 | X84: 13 | Y84: 15 | Z84: 100 | AA84: 100 | AB84: 100 | AC84: 100 | AD84: 100 | AE84: 100 | AF84: 100 | AG84: 100 | AH84: 100 | AI84: 100 | AJ84: 100 | AK84: 100 | AL84: 100 | AM84: 100 | AN84: 100 | AO84: 100 | AP84: 100 | AQ84: 100 | AR84: 100 | AS84: 100 | AT84: 100 | AU84: 3
A85: m | B85: 2 | C85: 1 | D85: 0 | E85: 3 | F85: 2 | G85: 3 | H85: 4 | I85: 5 | J85: 6 | K85: 6 | L85: 7 | M85: 7 | N85: 6 | O85: 7 | P85: 8 | Q85: 9 | R85: 10 | S85: 8 | T85: 9 | U85: 13 | V85: 12 | W85: 13 | X85: 12 | Y85: 14 | Z85: 100 | AA85: 100 | AB85: 100 | AC85: 100 | AD85: 100 | AE85: 100 | AF85: 100 | AG85: 100 | AH85: 100 | AI85: 100 | AJ85: 100 | AK85: 100 | AL85: 100 | AM85: 100 | AN85: 100 | AO85: 100 | AP85: 100 | AQ85: 100 | AR85: 100 | AS85: 100 | AT85: 100 | AU85: 4
A86: w | B86: 5 | C86: 4 | D86: 3 | E86: 0 | F86: 3 | G86: 4 | H86: 5 | I86: 6 | J86: 9 | K86: 7 | L86: 6 | M86: 10 | N86: 9 | O86: 8 | P86: 7 | Q86: 6 | R86: 7 | S86: 9 | T86: 10 | U86: 10 | V86: 15 | W86: 16 | X86: 15 | Y86: 15 | Z86: 100 | AA86: 100 | AB86: 100 | AC86: 100 | AD86: 100 | AE86: 100 | AF86: 100 | AG86: 100 | AH86: 100 | AI86: 100 | AJ86: 100 | AK86: 100 | AL86: 100 | AM86: 100 | AN86: 100 | AO86: 100 | AP86: 100 | AQ86: 100 | AR86: 100 | AS86: 100 | AT86: 100 | AU86: 5
A87: f | B87: 4 | C87: 3 | D87: 2 | E87: 3 | F87: 0 | G87: 1 | H87: 2 | I87: 3 | J87: 6 | K87: 4 | L87: 5 | M87: 7 | N87: 6 | O87: 5 | P87: 6 | Q87: 7 | R87: 8 | S87: 6 | T87: 7 | U87: 11 | V87: 12 | W87: 13 | X87: 12 | Y87: 12 | Z87: 100 | AA87: 100 | AB87: 100 | AC87: 100 | AD87: 100 | AE87: 100 | AF87: 100 | AG87: 100 | AH87: 100 | AI87: 100 | AJ87: 100 | AK87: 100 | AL87: 100 | AM87: 100 | AN87: 100 | AO87: 100 | AP87: 100 | AQ87: 100 | AR87: 100 | AS87: 100 | AT87: 100 | AU87: 6
A88: v | B88: 5 | C88: 4 | D88: 3 | E88: 2 | F88: 1 | G88: 0 | H88: 1 | I88: 2 | J88: 5 | K88: 3 | L88: 4 | M88: 6 | N88: 5 | O88: 4 | P88: 5 | Q88: 6 | R88: 7 | S88: 5 | T88: 6 | U88: 10 | V88: 11 | W88: 12 | X88: 11 | Y88: 11 | Z88: 100 | AA88: 100 | AB88: 100 | AC88: 100 | AD88: 100 | AE88: 100 | AF88: 100 | AG88: 100 | AH88: 100 | AI88: 100 | AJ88: 100 | AK88: 100 | AL88: 100 | AM88: 100 | AN88: 100 | AO88: 100 | AP88: 100 | AQ88: 100 | AR88: 100 | AS88: 100 | AT88: 100 | AU88: 7
A89: θ | B89: 5 | C89: 5 | D89: 4 | E89: 5 | F89: 2 | G89: 1 | H89: 0 | I89: 1 | J89: 4 | K89: 2 | L89: 3 | M89: 5 | N89: 4 | O89: 3 | P89: 4 | Q89: 5 | R89: 6 | S89: 4 | T89: 5 | U89: 9 | V89: 10 | W89: 11 | X89: 10 | Y89: 10 | Z89: 100 | AA89: 100 | AB89: 100 | AC89: 100 | AD89: 100 | AE89: 100 | AF89: 100 | AG89: 100 | AH89: 100 | AI89: 100 | AJ89: 100 | AK89: 100 | AL89: 100 | AM89: 100 | AN89: 100 | AO89: 100 | AP89: 100 | AQ89: 100 | AR89: 100 | AS89: 100 | AT89: 100 | AU89: 8
A90: ð | B90: 4 | C90: 6 | D90: 5 | E90: 6 | F90: 3 | G90: 2 | H90: 1 | I90: 0 | J90: 3 | K90: 1 | L90: 2 | M90: 4 | N90: 3 | O90: 2 | P90: 3 | Q90: 4 | R90: 5 | S90: 3 | T90: 4 | U90: 8 | V90: 9 | W90: 10 | X90: 9 | Y90: 9 | Z90: 100 | AA90: 100 | AB90: 100 | AC90: 100 | AD90: 100 | AE90: 100 | AF90: 100 | AG90: 100 | AH90: 100 | AI90: 100 | AJ90: 100 | AK90: 100 | AL90: 100 | AM90: 100 | AN90: 100 | AO90: 100 | AP90: 100 | AQ90: 100 | AR90: 100 | AS90: 100 | AT90: 100 | AU90: 9
A91: t | B91: 5 | C91: 5 | D91: 6 | E91: 9 | F91: 6 | G91: 5 | H91: 4 | I91: 3 | J91: 0 | K91: 2 | L91: 3 | M91: 1 | N91: 2 | O91: 3 | P91: 4 | Q91: 5 | R91: 6 | S91: 4 | T91: 5 | U91: 9 | V91: 6 | W91: 7 | X91: 8 | Y91: 10 | Z91: 100 | AA91: 100 | AB91: 100 | AC91: 100 | AD91: 100 | AE91: 100 | AF91: 100 | AG91: 100 | AH91: 100 | AI91: 100 | AJ91: 100 | AK91: 100 | AL91: 100 | AM91: 100 | AN91: 100 | AO91: 100 | AP91: 100 | AQ91: 100 | AR91: 100 | AS91: 100 | AT91: 100 | AU91: 10
A92: s | B92: 4 | C92: 6 | D92: 6 | E92: 7 | F92: 4 | G92: 3 | H92: 2 | I92: 1 | J92: 2 | K92: 0 | L92: 1 | M92: 3 | N92: 2 | O92: 1 | P92: 2 | Q92: 3 | R92: 4 | S92: 2 | T92: 3 | U92: 7 | V92: 8 | W92: 9 | X92: 8 | Y92: 8 | Z92: 100 | AA92: 100 | AB92: 100 | AC92: 100 | AD92: 100 | AE92: 100 | AF92: 100 | AG92: 100 | AH92: 100 | AI92: 100 | AJ92: 100 | AK92: 100 | AL92: 100 | AM92: 100 | AN92: 100 | AO92: 100 | AP92: 100 | AQ92: 100 | AR92: 100 | AS92: 100 | AT92: 100 | AU92: 11
A93: ʧ | B93: 5 | C93: 7 | D93: 7 | E93: 6 | F93: 5 | G93: 4 | H93: 3 | I93: 2 | J93: 3 | K93: 1 | L93: 0 | M93: 4 | N93: 3 | O93: 2 | P93: 1 | Q93: 2 | R93: 3 | S93: 3 | T93: 4 | U93: 6 | V93: 9 | W93: 10 | X93: 9 | Y93: 9 | Z93: 100 | AA93: 100 | AB93: 100 | AC93: 100 | AD93: 100 | AE93: 100 | AF93: 100 | AG93: 100 | AH93: 100 | AI93: 100 | AJ93: 100 | AK93: 100 | AL93: 100 | AM93: 100 | AN93: 100 | AO93: 100 | AP93: 100 | AQ93: 100 | AR93: 100 | AS93: 100 | AT93: 100 | AU93: 12
A94: d | B94: 4 | C94: 6 | D94: 7 | E94: 10 | F94: 7 | G94: 6 | H94: 5 | I94: 4 | J94: 1 | K94: 3 | L94: 4 | M94: 0 | N94: 1 | O94: 2 | P94: 3 | Q94: 4 | R94: 5 | S94: 3 | T94: 4 | U94: 7 | V94: 5 | W94: 6 | X94: 7 | Y94: 9 | Z94: 100 | AA94: 100 | AB94: 100 | AC94: 100 | AD94: 100 | AE94: 100 | AF94: 100 | AG94: 100 | AH94: 100 | AI94: 100 | AJ94: 100 | AK94: 100 | AL94: 100 | AM94: 100 | AN94: 100 | AO94: 100 | AP94: 100 | AQ94: 100 | AR94: 100 | AS94: 100 | AT94: 100 | AU94: 13
... A127: jʊə | B127: 100 | C127: 100 | D127: 100 | E127: 100 | F127: 100 | G127: 100 | H127: 100 | I127: 100 | J127: 100 | K127: 100 | L127: 100 | M127: 100 | N127: 100 | O127: 100 | P127: 100 | Q127: 100 | R127: 100 | S127: 100 | T127: 100 | U127: 100 | V127: 100 | W127: 100 | X127: 100 | Y127: 100 | Z127: 9 | AA127: 8 | AB127: 7 | AC127: 6 | AD127: 5 | AE127: 4 | AF127: 8 | AG127: 7 | AH127: 6 | AI127: 5 | AJ127: 4 | AK127: 7 | AL127: 6 | AM127: 5 | AN127: 6 | AO127: 5 | AP127: 4 | AQ127: 3 | AR127: 2 | AS127: 1 | AT127: 0 | AU127: 46
A146: conversion chart 2 | B146: p | C146: b | D146: m | E146: w | F146: f | G146: v | H146: θ | I146: ð | J146: t | K146: s | L146: ʧ | M146: d | N146: n | O146: z | P146: ʤ | Q146: r | R146: l | S146: ʃ | T146: ʒ | U146: jə | V146: k | W146: g | X146: ŋ | Y146: h | Z146: æ | AA146: ɛ | AB146: ɪ | AC146: ɒ | AD146: ʌ | AE146: ʊ | AF146: eɪ | AG146: i | AH146: aɪ | AI146: əʊ | AJ146: u | AK146: ɑ | AL146: ɜ | AM146: ɔ | AN146: ju | AO146: ɔɪ | AP146: aʊ | AQ146: ə | AR146: e | AS146: ɪə | AT146: jʊə
A147: p | B147: 1 | C147: 0.75 | D147: 0.56 | E147: 0.24 | F147: 0.32 | G147: 0.24 | H147: 0.18 | I147: 0.13 | J147: 0.18 | K147: 0.13 | L147: 0.1 | M147: 0.13 | N147: 0.1 | O147: 0.08 | P147: 0.06 | Q147: 0.04 | R147: 0.03 | S147: 0.06 | T147: 0.04 | U147: 0.01 | V147: 0.03 | W147: 0.02 | X147: 0.02 | Y147: 0.01 | Z147: 0 | AA147: 0 | AB147: 0 | AC147: 0 | AD147: 0 | AE147: 0 | AF147: 0 | AG147: 0 | AH147: 0 | AI147: 0 | AJ147: 0 | AK147: 0 | AL147: 0 | AM147: 0 | AN147: 0 | AO147: 0 | AP147: 0 | AQ147: 0 | AR147: 0 | AS147: 0 | AT147: 0
A148: b | B148: 0.75 | C148: 1 | D148: 0.75 | E148: 0.32 | F148: 0.42 | G148: 0.32 | H148: 0.24 | I148: 0.18 | J148: 0.24 | K148: 0.18 | L148: 0.13 | M148: 0.18 | N148: 0.13 | O148: 0.1 | P148: 0.08 | Q148: 0.06 | R148: 0.04 | S148: 0.08 | T148: 0.06 | U148: 0.02 | V148: 0.04 | W148: 0.03 | X148: 0.02 | Y148: 0.01 | Z148: 0 | AA148: 0 | AB148: 0 | AC148: 0 | AD148: 0 | AE148: 0 | AF148: 0 | AG148: 0 | AH148: 0 | AI148: 0 | AJ148: 0 | AK148: 0 | AL148: 0 | AM148: 0 | AN148: 0 | AO148: 0 | AP148: 0 | AQ148: 0 | AR148: 0 | AS148: 0 | AT148: 0
A149: m | B149: 0.56 | C149: 0.75 | D149: 1 | E149: 0.42 | F149: 0.56 | G149: 0.42 | H149: 0.32 | I149: 0.24 | J149: 0.18 | K149: 0.18 | L149: 0.13 | M149: 0.13 | N149: 0.18 | O149: 0.13 | P149: 0.1 | Q149: 0.08 | R149: 0.06 | S149: 0.1 | T149: 0.08 | U149: 0.02 | V149: 0.03 | W149: 0.02 | X149: 0.03 | Y149: 0.02 | Z149: 0 | AA149: 0 | AB149: 0 | AC149: 0 | AD149: 0 | AE149: 0 | AF149: 0 | AG149: 0 | AH149: 0 | AI149: 0 | AJ149: 0 | AK149: 0 | AL149: 0 | AM149: 0 | AN149: 0 | AO149: 0 | AP149: 0 | AQ149: 0 | AR149: 0 | AS149: 0 | AT149: 0
A150: w | B150: 0.24 | C150: 0.32 | D150: 0.42 | E150: 1 | F150: 0.42 | G150: 0.32 | H150: 0.24 | I150: 0.18 | J150: 0.08 | K150: 0.13 | L150: 0.18 | M150: 0.06 | N150: 0.08 | O150: 0.1 | P150: 0.13 | Q150: 0.18 | R150: 0.13 | S150: 0.08 | T150: 0.06 | U150: 0.06 | V150: 0.01 | W150: 0.01 | X150: 0.01 | Y150: 0.01 | Z150: 0 | AA150: 0 | AB150: 0 | AC150: 0 | AD150: 0 | AE150: 0 | AF150: 0 | AG150: 0 | AH150: 0 | AI150: 0 | AJ150: 0 | AK150: 0 | AL150: 0 | AM150: 0 | AN150: 0 | AO150: 0 | AP150: 0 | AQ150: 0 | AR150: 0 | AS150: 0 | AT150: 0
A151: f | B151: 0.32 | C151: 0.42 | D151: 0.56 | E151: 0.42 | F151: 1 | G151: 0.75 | H151: 0.56 | I151: 0.42 | J151: 0.18 | K151: 0.32 | L151: 0.24 | M151: 0.13 | N151: 0.18 | O151: 0.24 | P151: 0.18 | Q151: 0.13 | R151: 0.1 | S151: 0.18 | T151: 0.13 | U151: 0.04 | V151: 0.03 | W151: 0.02 | X151: 0.03 | Y151: 0.03 | Z151: 0 | AA151: 0 | AB151: 0 | AC151: 0 | AD151: 0 | AE151: 0 | AF151: 0 | AG151: 0 | AH151: 0 | AI151: 0 | AJ151: 0 | AK151: 0 | AL151: 0 | AM151: 0 | AN151: 0 | AO151: 0 | AP151: 0 | AQ151: 0 | AR151: 0 | AS151: 0 | AT151: 0
A152: v | B152: 0.24 | C152: 0.32 | D152: 0.42 | E152: 0.56 | F152: 0.75 | G152: 1 | H152: 0.75 | I152: 0.56 | J152: 0.24 | K152: 0.42 | L152: 0.32 | M152: 0.18 | N152: 0.24 | O152: 0.32 | P152: 0.24 | Q152: 0.18 | R152: 0.13 | S152: 0.24 | T152: 0.18 | U152: 0.06 | V152: 0.04 | W152: 0.03 | X152: 0.04 | Y152: 0.04 | Z152: 0 | AA152: 0 | AB152: 0 | AC152: 0 | AD152: 0 | AE152: 0 | AF152: 0 | AG152: 0 | AH152: 0 | AI152: 0 | AJ152: 0 | AK152: 0 | AL152: 0 | AM152: 0 | AN152: 0 | AO152: 0 | AP152: 0 | AQ152: 0 | AR152: 0 | AS152: 0 | AT152: 0
A153: θ | B153: 0.24 | C153: 0.24 | D153: 0.32 | E153: 0.24 | F153: 0.56 | G153: 0.75 | H153: 1 | I153: 0.75 | J153: 0.32 | K153: 0.56 | L153: 0.42 | M153: 0.24 | N153: 0.32 | O153: 0.42 | P153: 0.32 | Q153: 0.24 | R153: 0.18 | S153: 0.32 | T153: 0.24 | U153: 0.08 | V153: 0.06 | W153: 0.04 | X153: 0.06 | Y153: 0.06 | Z153: 0 | AA153: 0 | AB153: 0 | AC153: 0 | AD153: 0 | AE153: 0 | AF153: 0 | AG153: 0 | AH153: 0 | AI153: 0 | AJ153: 0 | AK153: 0 | AL153: 0 | AM153: 0 | AN153: 0 | AO153: 0 | AP153: 0 | AQ153: 0 | AR153: 0 | AS153: 0 | AT153: 0
A154: ð | B154: 0.32 | C154: 0.18 | D154: 0.24 | E154: 0.18 | F154: 0.42 | G154: 0.56 | H154: 0.75 | I154: 1 | J154: 0.42 | K154: 0.75 | L154: 0.56 | M154: 0.32 | N154: 0.42 | O154: 0.56 | P154: 0.42 | Q154: 0.32 | R154: 0.24 | S154: 0.42 | T154: 0.32 | U154: 0.1 | V154: 0.08 | W154: 0.06 | X154: 0.08 | Y154: 0.08 | Z154: 0 | AA154: 0 | AB154: 0 | AC154: 0 | AD154: 0 | AE154: 0 | AF154: 0 | AG154: 0 | AH154: 0 | AI154: 0 | AJ154: 0 | AK154: 0 | AL154: 0 | AM154: 0 | AN154: 0 | AO154: 0 | AP154: 0 | AQ154: 0 | AR154: 0 | AS154: 0 | AT154: 0
A155: t | B155: 0.24 | C155: 0.24 | D155: 0.18 | E155: 0.08 | F155: 0.18 | G155: 0.24 | H155: 0.32 | I155: 0.42 | J155: 1 | K155: 0.56 | L155: 0.42 | M155: 0.75 | N155: 0.56 | O155: 0.42 | P155: 0.32 | Q155: 0.24 | R155: 0.18 | S155: 0.32 | T155: 0.24 | U155: 0.08 | V155: 0.18 | W155: 0.13 | X155: 0.1 | Y155: 0.06 | Z155: 0 | AA155: 0 | AB155: 0 | AC155: 0 | AD155: 0 | AE155: 0 | AF155: 0 | AG155: 0 | AH155: 0 | AI155: 0 | AJ155: 0 | AK155: 0 | AL155: 0 | AM155: 0 | AN155: 0 | AO155: 0 | AP155: 0 | AQ155: 0 | AR155: 0 | AS155: 0 | AT155: 0
A156: s | B156: 0.32 | C156: 0.18 | D156: 0.18 | E156: 0.13 | F156: 0.32 | G156: 0.42 | H156: 0.56 | I156: 0.75 | J156: 0.56 | K156: 1 | L156: 0.75 | M156: 0.42 | N156: 0.56 | O156: 0.75 | P156: 0.56 | Q156: 0.42 | R156: 0.32 | S156: 0.56 | T156: 0.42 | U156: 0.13 | V156: 0.1 | W156: 0.08 | X156: 0.1 | Y156: 0.1 | Z156: 0 | AA156: 0 | AB156: 0 | AC156: 0 | AD156: 0 | AE156: 0 | AF156: 0 | AG156: 0 | AH156: 0 | AI156: 0 | AJ156: 0 | AK156: 0 | AL156: 0 | AM156: 0 | AN156: 0 | AO156: 0 | AP156: 0 | AQ156: 0 | AR156: 0 | AS156: 0 | AT156: 0
A157: ʧ | B157: 0.24 | C157: 0.13 | D157: 0.13 | E157: 0.18 | F157: 0.24 | G157: 0.32 | H157: 0.42 | I157: 0.56 | J157: 0.42 | K157: 0.75 | L157: 1 | M157: 0.32 | N157: 0.42 | O157: 0.56 | P157: 0.75 | Q157: 0.56 | R157: 0.42 | S157: 0.42 | T157: 0.32 | U157: 0.18 | V157: 0.08 | W157: 0.06 | X157: 0.08 | Y157: 0.08 | Z157: 0 | AA157: 0 | AB157: 0 | AC157: 0 | AD157: 0 | AE157: 0 | AF157: 0 | AG157: 0 | AH157: 0 | AI157: 0 | AJ157: 0 | AK157: 0 | AL157: 0 | AM157: 0 | AN157: 0 | AO157: 0 | AP157: 0 | AQ157: 0 | AR157: 0 | AS157: 0 | AT157: 0
A158: d | B158: 0.32 | C158: 0.18 | D158: 0.13 | E158: 0.06 | F158: 0.13 | G158: 0.18 | H158: 0.24 | I158: 0.32 | J158: 0.75 | K158: 0.42 | L158: 0.32 | M158: 1 | N158: 0.75 | O158: 0.56 | P158: 0.42 | Q158: 0.32 | R158: 0.24 | S158: 0.42 | T158: 0.32 | U158: 0.13 | V158: 0.24 | W158: 0.18 | X158: 0.13 | Y158: 0.08 | Z158: 0 | AA158: 0 | AB158: 0 | AC158: 0 | AD158: 0 | AE158: 0 | AF158: 0 | AG158: 0 | AH158: 0 | AI158: 0 | AJ158: 0 | AK158: 0 | AL158: 0 | AM158: 0 | AN158: 0 | AO158: 0 | AP158: 0 | AQ158: 0 | AR158: 0 | AS158: 0 | AT158: 0
... A191: jʊə | B191: 0 | C191: 0 | D191: 0 | E191: 0 | F191: 0 | G191: 0 | H191: 0 | I191: 0 | J191: 0 | K191: 0 | L191: 0 | M191: 0 | N191: 0 | O191: 0 | P191: 0 | Q191: 0 | R191: 0 | S191: 0 | T191: 0 | U191: 0 | V191: 0 | W191: 0 | X191: 0 | Y191: 0 | Z191: 0.08 | AA191: 0.1 | AB191: 0.13 | AC191: 0.18 | AD191: 0.24 | AE191: 0.32 | AF191: 0.1 | AG191: 0.13 | AH191: 0.18 | AI191: 0.24 | AJ191: 0.32 | AK191: 0.13 | AL191: 0.18 | AM191: 0.24 | AN191: 0.18 | AO191: 0.24 | AP191: 0.32 | AQ191: 0.42 | AR191: 0.56 | AS191: 0.75 | AT191: 1
A201: Random | B201: p | C201: b | D201: m | E201: w | F201: f | G201: v | H201: θ | I201: ð | J201: t | K201: s | L201: ʧ | M201: d | N201: n | O201: z | P201: ʤ | Q201: r | R201: l | S201: ʃ | T201: ʒ | U201: jə | V201: k | W201: g | X201: ŋ | Y201: h | Z201: " | AA201: æ | AB201: ɛ | AC201: ɪ | AD201: ɒ | AE201: ʌ | AF201: ʊ | AG201: eɪ | AH201: i | AI201: aɪ | AJ201: əʊ | AK201: u | AL201: ɑ | AM201: ɜ | AN201: ɔ | AO201: ju | AP201: ɔɪ | AQ201: aʊ | AR201: ə | AS201: e | AT201: ɪə | AU201: jʊə
B202: 0.02567956 | C202: 0.37186586 | D202: 0.39804911 | E202: 0.78084395 | F202: 0.80665169 | G202: 0.56341005 | H202: 0.26054465 | I202: 0.58481938 | J202: 0.21079809 | K202: 0.90851636 | L202: 0.56683394 | M202: 0.11912796 | N202: 0.29979669 | O202: 0.053627252 | P202: 0.53820009 | Q202: 0.91622547 | R202: 0.51930342 | S202: 0.88217879 | T202: 0.21623417 | U202: 0.033537647 | V202: 0.81129449 | W202: 0.34424543 | X202: 0.40380458 | Y202: 0.17435203 | Z202: 0.72800037 | AA202: 0.52801856 | AB202: 0.092801801 | AC202: 0.065145998 | AD202: 0.94870707 | AE202: 0.37268532 | AF202: 0.2237819 | AG202: 0.34292168 | AH202: 0.9649581 | AI202: 0.16934483 | AJ202: 0.56501475 | AK202: 0.65631379 | AL202: 0.47019861 | AM202: 0.39991882 | AN202: 0.34707602 | AO202: 0.29068129 | AP202: 0.1666605 | AQ202: 0.5235846 | AR202: 0.04400458 | AS202: 0.39008948 | AT202: 0.28529555 | AU202: 0.036077948
A204: Speech number | B204: p | C204: b | D204: m | E204: w | F204: f | G204: v | H204: θ | I204: ð | J204: t | K204: s | L204: ʧ | M204: d | N204: n | O204: z | P204: ʤ | Q204: r | R204: l | S204: ʃ | T204: ʒ | U204: jə | V204: k | W204: g | X204: ŋ | Y204: h | Z204: " | AA204: æ | AB204: ɛ | AC204: ɪ | AD204: ɒ | AE204: ʌ | AF204: ʊ | AG204: eɪ | AH204: i | AI204: aɪ | AJ204: əʊ | AK204: u | AL204: ɑ | AM204: ɜ | AN204: ɔ | AO204: ju | AP204: ɔɪ | AQ204: aʊ | AR204: ə | AS204: e | AT204: ɪə | AU204: jʊə
B205: 0.0625 | C205: 0.125 | D205: 0.10416667 | E205: 0.041666667 | F205: 0.125 | G205: 0.16666667 | H205: 0.20833333 | I205: 0.25 | J205: 0.4375 | K205: 0.33333333 | L205: 0.21875 | M205: 0.5 | N205: 0.41666667 | O205: 0.33333333 | P205: 0.25 | Q205: 0.16666667 | R205: 0.083333333 | S205: 0.375 | T205: 0.41666667 | U205: 0.25 | V205: 0.8125 | W205: 0.875 | X205: 0.72916667 | Y205: 0.625 | Z205: 0.72800037 | AA205: 0.25 | AB205: 0.21428571 | AC205: 0.17857143 | AD205: 0.14285714 | AE205: 0.10714286 | AF205: 0.071428571 | AG205: 0.5 | AH205: 0.42857143 | AI205: 0.35714286 | AJ205: 0.28571429 | AK205: 0.14285714 | AL205: 0.75 | AM205: 0.64285714 | AN205: 0.53571429 | AO205: 1 | AP205: 0.85714286 | AQ205: 0.71428571 | AR205: 0.57142857 | AS205: 0.42857143 | AT205: 0.28571429 | AU205: 0.14285714
A207: Total | B207: =B202*B205 -> 0.0016049725 | C207: =C202*C205 -> 0.046483232 | D207: =D202*D205 -> 0.041463449 | E207: =E202*E205 -> 0.032535165 | F207: =F202*F205 -> 0.10083146 | G207: =G202*G205 -> 0.093901675 | H207: =H202*H205 -> 0.054280136 | I207: =I202*I205 -> 0.14620485 | ... AU207: =AU202*AU205 -> 0.0051539926
A212: conversion chart 3 | B212: p | C212: b | D212: m | E212: w | F212: f | G212: v | H212: θ | I212: ð | J212: t | K212: s | L212: ʧ | M212: d | N212: n | O212: z | P212: ʤ | Q212: r | R212: l | S212: ʃ | T212: ʒ | U212: jə | V212: k | W212: g | X212: ŋ | Y212: h | Z212: " | AA212: æ | AB212: ɛ | AC212: ɪ | AD212: ɒ | AE212: ʌ | AF212: ʊ | AG212: eɪ | AH212: i | AI212: aɪ | AJ212: əʊ | AK212: u | AL212: ɑ | AM212: ɜ | AN212: ɔ | AO212: ju | AP212: ɔɪ | AQ212: aʊ | AR212: ə | AS212: e | AT212: ɪə | AU212: jʊə
A213: p | B213: 0.0016049725 | C213: 0.034862424 | D213: 0.023219532 | E213: 0.0078084395 | F213: 0.032266068 | G213: 0.022536402 | H213: 0.0097704244 | I213: 0.01900663 | J213: 0.016600349 | K213: 0.039369042 | L213: 0.012399492 | M213: 0.0077433174 | N213: 0.012491529 | O213: 0.0014300601 | P213: 0.0080730014 | Q213: 0.0061081698 | R213: 0.0012982586 | S213: 0.019849023 | T213: 0.0036039029 | U213: 8.3844116e-05 | V213: 0.019775303 | W213: 0.006024295 | X213: 0.0058888168 | Y213: 0.0010897002 | Z213: 0.72800037 | AA213: 0 | AB213: 0 | AC213: 0 | AD213: 0 | AE213: 0 | AF213: 0 | AG213: 0 | AH213: 0 | AI213: 0 | AJ213: 0 | AK213: 0 | AL213: 0 | AM213: 0 | AN213: 0 | AO213: 0 | AP213: 0 | AQ213: 0 | AR213: 0 | AS213: 0 | AT213: 0 | AU213: 0 | AV213: 1.0409034
A214: b | B214: 0.0012037294 | C214: 0.046483232 | D214: 0.031097587 | E214: 0.010411253 | F214: 0.042349214 | G214: 0.030048536 | H214: 0.013027233 | I214: 0.026316872 | J214: 0.022133799 | K214: 0.054510982 | L214: 0.01611934 | M214: 0.010721516 | N214: 0.016238988 | O214: 0.0017875751 | P214: 0.010764002 | Q214: 0.0091622547 | R214: 0.0017310114 | S214: 0.026465364 | T214: 0.0054058544 | U214: 0.00016768823 | V214: 0.026367071 | W214: 0.0090364424 | X214: 0.0058888168 | Y214: 0.0010897002 | Z214: 0.72800037 | AA214: 0 | AB214: 0 | AC214: 0 | AD214: 0 | AE214: 0 | AF214: 0 | AG214: 0 | AH214: 0 | AI214: 0 | AJ214: 0 | AK214: 0 | AL214: 0 | AM214: 0 | AN214: 0 | AO214: 0 | AP214: 0 | AQ214: 0 | AR214: 0 | AS214: 0 | AT214: 0 | AU214: 0 | AV214: 1.1465284
A215: m | B215: 0.00089878461 | C215: 0.034862424 | D215: 0.041463449 | E215: 0.013664769 | F215: 0.056465619 | G215: 0.039438703 | H215: 0.017369643 | I215: 0.035089163 | J215: 0.016600349 | K215: 0.054510982 | L215: 0.01611934 | M215: 0.0077433174 | N215: 0.022484752 | O215: 0.0023238476 | P215: 0.013455002 | Q215: 0.01221634 | R215: 0.0025965171 | S215: 0.033081705 | T215: 0.0072078058 | U215: 0.00016768823 | V215: 0.019775303 | W215: 0.006024295 | X215: 0.0088332252 | Y215: 0.0021794003 | Z215: 0.72800037 | AA215: 0 | AB215: 0 | AC215: 0 | AD215: 0 | AE215: 0 | AF215: 0 | AG215: 0 | AH215: 0 | AI215: 0 | AJ215: 0 | AK215: 0 | AL215: 0 | AM215: 0 | AN215: 0 | AO215: 0 | AP215: 0 | AQ215: 0 | AR215: 0 | AS215: 0 | AT215: 0 | AU215: 0 | AV215: 1.1925728
A216: w | B216: 0.0003851934 | C216: 0.014874634 | D216: 0.017414649 | E216: 0.032535165 | F216: 0.042349214 | G216: 0.030048536 | H216: 0.013027233 | I216: 0.026316872 | J216: 0.0073779331 | K216: 0.039369042 | L216: 0.022319086 | M216: 0.0035738388 | N216: 0.0099932231 | O216: 0.0017875751 | P216: 0.017491503 | Q216: 0.027486764 | R216: 0.0056257871 | S216: 0.026465364 | T216: 0.0054058544 | U216: 0.0005030647 | V216: 0.0065917677 | W216: 0.0030121475 | X216: 0.0029444084 | Y216: 0.0010897002 | Z216: 0.72800037 | AA216: 0 | AB216: 0 | AC216: 0 | AD216: 0 | AE216: 0 | AF216: 0 | AG216: 0 | AH216: 0 | AI216: 0 | AJ216: 0 | AK216: 0 | AL216: 0 | AM216: 0 | AN216: 0 | AO216: 0 | AP216: 0 | AQ216: 0 | AR216: 0 | AS216: 0 | AT216: 0 | AU216: 0 | AV216: 1.0859889
A217: f | B217: 0.00051359121 | C217: 0.019522958 | D217: 0.023219532 | E217: 0.013664769 | F217: 0.10083146 | G217: 0.070426256 | H217: 0.030396876 | I217: 0.061406035 | J217: 0.016600349 | K217: 0.096908412 | L217: 0.029758782 | M217: 0.0077433174 | N217: 0.022484752 | O217: 0.0042901802 | P217: 0.024219004 | Q217: 0.019851552 | R217: 0.0043275285 | S217: 0.059547068 | T217: 0.011712684 | U217: 0.00033537647 | V217: 0.019775303 | W217: 0.006024295 | X217: 0.0088332252 | Y217: 0.0032691005 | Z217: 0.72800037 | AA217: 0 | AB217: 0 | AC217: 0 | AD217: 0 | AE217: 0 | AF217: 0 | AG217: 0 | AH217: 0 | AI217: 0 | AJ217: 0 | AK217: 0 | AL217: 0 | AM217: 0 | AN217: 0 | AO217: 0 | AP217: 0 | AQ217: 0 | AR217: 0 | AS217: 0 | AT217: 0 | AU217: 0 | AV217: 1.3836628
A218: v | B218: 0.0003851934 | C218: 0.014874634 | D218: 0.017414649 | E218: 0.018219692 | F218: 0.075623596 | G218: 0.093901675 | H218: 0.040710102 | I218: 0.081874714 | J218: 0.022133799 | K218: 0.12719229 | L218: 0.039678376 | M218: 0.010721516 | N218: 0.029979669 | O218: 0.0057202402 | P218: 0.032292005 | Q218: 0.027486764 | R218: 0.0056257871 | S218: 0.079396091 | T218: 0.016217563 | U218: 0.0005030647 | V218: 0.026367071 | W218: 0.0090364424 | X218: 0.011777634 | Y218: 0.0043588007 | Z218: 0.72800037 | AA218: 0 | AB218: 0 | AC218: 0 | AD218: 0 | AE218: 0 | AF218: 0 | AG218: 0 | AH218: 0 | AI218: 0 | AJ218: 0 | AK218: 0 | AL218: 0 | AM218: 0 | AN218: 0 | AO218: 0 | AP218: 0 | AQ218: 0 | AR218: 0 | AS218: 0 | AT218: 0 | AU218: 0 | AV218: 1.5194917
A219: θ | B219: 0.0003851934 | C219: 0.011155976 | D219: 0.013268304 | E219: 0.0078084395 | F219: 0.056465619 | G219: 0.070426256 | H219: 0.054280136 | I219: 0.10965363 | J219: 0.029511732 | K219: 0.16958972 | L219: 0.052077868 | M219: 0.014295355 | N219: 0.039972892 | O219: 0.0075078153 | P219: 0.043056007 | Q219: 0.036649019 | R219: 0.0077895513 | S219: 0.10586145 | T219: 0.021623417 | U219: 0.00067075293 | V219: 0.039550606 | W219: 0.01204859 | X219: 0.01766645 | Y219: 0.006538201 | Z219: 0.72800037 | AA219: 0 | AB219: 0 | AC219: 0 | AD219: 0 | AE219: 0 | AF219: 0 | AG219: 0 | AH219: 0 | AI219: 0 | AJ219: 0 | AK219: 0 | AL219: 0 | AM219: 0 | AN219: 0 | AO219: 0 | AP219: 0 | AQ219: 0 | AR219: 0 | AS219: 0 | AT219: 0 | AU219: 0 | AV219: 1.6558534
A220: ð | B220: 0.00051359121 | C220: 0.0083669818 | D220: 0.0099512279 | E220: 0.0058563296 | F220: 0.042349214 | G220: 0.052584938 | H220: 0.040710102 | I220: 0.14620485 | J220: 0.038734149 | K220: 0.22712909 | L220: 0.069437157 | M220: 0.019060474 | N220: 0.052464421 | O220: 0.01001042 | P220: 0.05651101 | Q220: 0.048865358 | R220: 0.010386068 | S220: 0.13894316 | T220: 0.028831223 | U220: 0.00083844116 | V220: 0.052734142 | W220: 0.018072885 | X220: 0.023555267 | Y220: 0.0087176014 | Z220: 0.72800037 | AA220: 0 | AB220: 0 | AC220: 0 | AD220: 0 | AE220: 0 | AF220: 0 | AG220: 0 | AH220: 0 | AI220: 0 | AJ220: 0 | AK220: 0 | AL220: 0 | AM220: 0 | AN220: 0 | AO220: 0 | AP220: 0 | AQ220: 0 | AR220: 0 | AS220: 0 | AT220: 0 | AU220: 0 | AV220: 1.8388285
A221: t | B221: 0.0003851934 | C221: 0.011155976 | D221: 0.0074634209 | E221: 0.0026028132 | F221: 0.018149663 | G221: 0.022536402 | H221: 0.017369643 | I221: 0.061406035 | J221: 0.092224164 | K221: 0.16958972 | L221: 0.052077868 | M221: 0.044672985 | N221: 0.069952562 | O221: 0.0075078153 | P221: 0.043056007 | Q221: 0.036649019 | R221: 0.0077895513 | S221: 0.10586145 | T221: 0.021623417 | U221: 0.00067075293 | V221: 0.11865182 | W221: 0.039157917 | X221: 0.029444084 | Y221: 0.006538201 | Z221: 0.72800037 | AA221: 0 | AB221: 0 | AC221: 0 | AD221: 0 | AE221: 0 | AF221: 0 | AG221: 0 | AH221: 0 | AI221: 0 | AJ221: 0 | AK221: 0 | AL221: 0 | AM221: 0 | AN221: 0 | AO221: 0 | AP221: 0 | AQ221: 0 | AR221: 0 | AS221: 0 | AT221: 0 | AU221: 0 | AV221: 1.7145369
A222: s | B222: 0.00051359121 | C222: 0.0083669818 | D222: 0.0074634209 | E222: 0.0042295714 | F222: 0.032266068 | G222: 0.039438703 | H222: 0.030396876 | I222: 0.10965363 | J222: 0.051645532 | K222: 0.30283879 | L222: 0.092996193 | M222: 0.025016872 | N222: 0.069952562 | O222: 0.013406813 | P222: 0.075348013 | Q222: 0.064135783 | R222: 0.013848091 | S222: 0.18525755 | T222: 0.037840981 | U222: 0.0010899735 | V222: 0.065917677 | W222: 0.02409718 | X222: 0.029444084 | Y222: 0.010897002 | Z222: 0.72800037 | AA222: 0 | AB222: 0 | AC222: 0 | AD222: 0 | AE222: 0 | AF222: 0 | AG222: 0 | AH222: 0 | AI222: 0 | AJ222: 0 | AK222: 0 | AL222: 0 | AM222: 0 | AN222: 0 | AO222: 0 | AP222: 0 | AQ222: 0 | AR222: 0 | AS222: 0 | AT222: 0 | AU222: 0 | AV222: 2.0240623
A223: ʧ | B223: 0.0003851934 | C223: 0.0060428202 | D223: 0.0053902484 | E223: 0.0058563296 | F223: 0.024199551 | G223: 0.030048536 | H223: 0.022797657 | I223: 0.081874714 | J223: 0.038734149 | K223: 0.22712909 | L223: 0.12399492 | M223: 0.019060474 | N223: 0.052464421 | O223: 0.01001042 | P223: 0.10091252 | Q223: 0.085514377 | R223: 0.01817562 | S223: 0.13894316 | T223: 0.028831223 | U223: 0.0015091941 | V223: 0.052734142 | W223: 0.018072885 | X223: 0.023555267 | Y223: 0.0087176014 | Z223: 0.72800037 | AA223: 0 | AB223: 0 | AC223: 0 | AD223: 0 | AE223: 0 | AF223: 0 | AG223: 0 | AH223: 0 | AI223: 0 | AJ223: 0 | AK223: 0 | AL223: 0 | AM223: 0 | AN223: 0 | AO223: 0 | AP223: 0 | AQ223: 0 | AR223: 0 | AS223: 0 | AT223: 0 | AU223: 0 | AV223: 1.8529549
A224: d | B224: 0.00051359121 | C224: 0.0083669818 | D224: 0.0053902484 | E224: 0.0019521099 | F224: 0.01310809 | G224: 0.016902301 | H224: 0.013027233 | I224: 0.046785551 | J224: 0.069168123 | K224: 0.12719229 | L224: 0.039678376 | M224: 0.05956398 | N224: 0.093686466 | O224: 0.01001042 | P224: 0.05651101 | Q224: 0.048865358 | R224: 0.010386068 | S224: 0.13894316 | T224: 0.028831223 | U224: 0.0010899735 | V224: 0.15820242 | W224: 0.054218655 | X224: 0.038277309 | Y224: 0.0087176014 | Z224: 0.72800037 | AA224: 0 | AB224: 0 | AC224: 0 | AD224: 0 | AE224: 0 | AF224: 0 | AG224: 0 | AH224: 0 | AI224: 0 | AJ224: 0 | AK224: 0 | AL224: 0 | AM224: 0 | AN224: 0 | AO224: 0 | AP224: 0 | AQ224: 0 | AR224: 0 | AS224: 0 | AT224: 0 | AU224: 0 | AV224: 1.7773889
... A257: jʊə | B257: 0 | C257: 0 | D257: 0 | E257: 0 | F257: 0 | G257: 0 | H257: 0 | I257: 0 | J257: 0 | K257: 0 | L257: 0 | M257: 0 | N257: 0 | O257: 0 | P257: 0 | Q257: 0 | R257: 0 | S257: 0 | T257: 0 | U257: 0 | V257: 0 | W257: 0 | X257: 0 | Y257: 0 | Z257: 0.72800037 | AA257: 0.010560371 | AB257: 0.00198861 | AC257: 0.0015123178 | AD257: 0.024395325 | AE257: 0.0095833368 | AF257: 0.0051150149 | AG257: 0.017146084 | AH257: 0.053761951 | AI257: 0.010886454 | AJ257: 0.038743869 | AK257: 0.030002916 | AL257: 0.045844365 | AM257: 0.046276321 | AN257: 0.04462406 | AO257: 0.052322633 | AP257: 0.034284446 | AQ257: 0.11967648 | AR257: 0.010561099 | AS257: 0.093621476 | AT257: 0.06113476 | AU257: 0.0051539926 | AV257: 1.4451962
A262: conversion chart 4 | B262: p | C262: b | D262: m | E262: w | F262: f | G262: v | H262: θ | I262: ð | J262: t | K262: s | L262: ʧ | M262: d | N262: n | O262: z | P262: ʤ | Q262: r | R262: l | S262: ʃ | T262: ʒ | U262: jə | V262: k | W262: g | X262: ŋ | Y262: h | Z262: " | AA262: æ | AB262: ɛ | AC262: ɪ | AD262: ɒ | AE262: ʌ | AF262: ʊ | AG262: eɪ | AH262: i | AI262: aɪ | AJ262: əʊ | AK262: u | AL262: ɑ | AM262: ɜ | AN262: ɔ | AO262: ju | AP262: ɔɪ | AQ262: aʊ | AR262: ə | AS262: e | AT262: ɪə | AU262: jʊə
A263: p | B263: 0.0015419035 | C263: 0.033492469 | D263: 0.022307096 | E263: 0.0075015989 | F263: 0.03099814 | G263: 0.021650811 | H263: 0.0093864856 | I263: 0.018259745 | J263: 0.015948022 | K263: 0.037821995 | L263: 0.011912242 | M263: 0.0074390358 | N263: 0.012000661 | O263: 0.0013738644 | P263: 0.0077557645 | Q263: 0.005868143 | R263: 0.0012472422 | S263: 0.019069035 | T263: 0.0034622838 | U263: 8.0549376e-05 | V263: 0.018998212 | W263: 0.0057875641 | X263: 0.0056574097 | Y263: 0.0010468793 | Z263: 0.69939285 | AA263: 0 | AB263: 0 | AC263: 0 | AD263: 0 | AE263: 0 | AF263: 0 | AG263: 0 | AH263: 0 | AI263: 0 | AJ263: 0 | AK263: 0 | AL263: 0 | AM263: 0 | AN263: 0 | AO263: 0 | AP263: 0 | AQ263: 0 | AR263: 0 | AS263: 0 | AT263: 0 | AU263: 0
A264: b | B264: 0.0010498906 | C264: 0.04054259 | D264: 0.027123259 | E264: 0.0090806756 | F264: 0.036936907 | G264: 0.026208278 | H264: 0.011362328 | I264: 0.022953528 | J264: 0.019305059 | K264: 0.047544378 | L264: 0.014059259 | M264: 0.009351287 | N264: 0.014163615 | O264: 0.0015591197 | P264: 0.0093883427 | Q264: 0.0079913018 | R264: 0.001509785 | S264: 0.023083042 | T264: 0.0047149763 | U264: 0.00014625737 | V264: 0.022997311 | W264: 0.0078815686 | X264: 0.0051362153 | Y264: 0.0009504345 | Z264: 0.63496059 | AA264: 0 | AB264: 0 | AC264: 0 | AD264: 0 | AE264: 0 | AF264: 0 | AG264: 0 | AH264: 0 | AI264: 0 | AJ264: 0 | AK264: 0 | AL264: 0 | AM264: 0 | AN264: 0 | AO264: 0 | AP264: 0 | AQ264: 0 | AR264: 0 | AS264: 0 | AT264: 0 | AU264: 0
A265: m | B265: 0.00075365178 | C265: 0.029232953 | D265: 0.034768066 | E265: 0.011458226 | F265: 0.047347733 | G265: 0.033070269 | H265: 0.01456485 | I265: 0.029423079 | J265: 0.013919779 | K265: 0.045708725 | L265: 0.013516441 | M265: 0.0064929516 | N265: 0.018853987 | O265: 0.0019486002 | P265: 0.011282332 | Q265: 0.010243685 | R265: 0.0021772399 | S265: 0.027739778 | T265: 0.0060439127 | U265: 0.00014061048 | V265: 0.016582051 | W265: 0.0050515113 | X265: 0.0074068646 | Y265: 0.0018274778 | Z265: 0.61044523 | AA265: 0 | AB265: 0 | AC265: 0 | AD265: 0 | AE265: 0 | AF265: 0 | AG265: 0 | AH265: 0 | AI265: 0 | AJ265: 0 | AK265: 0 | AL265: 0 | AM265: 0 | AN265: 0 | AO265: 0 | AP265: 0 | AQ265: 0 | AR265: 0 | AS265: 0 | AT265: 0 | AU265: 0
A266: w | B266: 0.00035469368 | C266: 0.013696856 | D266: 0.016035752 | E266: 0.029959021 | F266: 0.038995991 | G266: 0.027669284 | H266: 0.011995732 | I266: 0.024233095 | J266: 0.0067937462 | K266: 0.03625179 | L266: 0.020551854 | M266: 0.0032908612 | N266: 0.0092019567 | O266: 0.0016460343 | P266: 0.016106521 | Q266: 0.025310354 | R266: 0.0051803356 | S266: 0.024369828 | T266: 0.0049778172 | U266: 0.00046323189 | V266: 0.0060698296 | W266: 0.0027736447 | X266: 0.0027112693 | Y266: 0.0010034174 | Z266: 0.67035708 | AA266: 0 | AB266: 0 | AC266: 0 | AD266: 0 | AE266: 0 | AF266: 0 | AG266: 0 | AH266: 0 | AI266: 0 | AJ266: 0 | AK266: 0 | AL266: 0 | AM266: 0 | AN266: 0 | AO266: 0 | AP266: 0 | AQ266: 0 | AR266: 0 | AS266: 0 | AT266: 0 | AU266: 0
A267: f | B267: 0.00037118235 | C267: 0.014109621 | D267: 0.016781207 | E267: 0.0098757944 | F267: 0.072872859 | G267: 0.050898425 | H267: 0.021968413 | I267: 0.044379336 | J267: 0.011997395 | K267: 0.070037594 | L267: 0.02150725 | M267: 0.0055962461 | N267: 0.016250168 | O267: 0.0031005966 | P267: 0.017503545 | Q267: 0.014347103 | R267: 0.003127589 | S267: 0.043035824 | T267: 0.0084649849 | U267: 0.00024238309 | V267: 0.014291996 | W267: 0.0043538751 | X267: 0.0063839437 | Y267: 0.0023626425 | Z267: 0.52614003 | AA267: 0 | AB267: 0 | AC267: 0 | AD267: 0 | AE267: 0 | AF267: 0 | AG267: 0 | AH267: 0 | AI267: 0 | AJ267: 0 | AK267: 0 | AL267: 0 | AM267: 0 | AN267: 0 | AO267: 0 | AP267: 0 | AQ267: 0 | AR267: 0 | AS267: 0 | AT267: 0 | AU267: 0
A268: v | B268: 0.00025350148 | C268: 0.009789217 | D268: 0.011460838 | E268: 0.011990649 | F268: 0.049769008 | G268: 0.061798082 | H268: 0.02679192 | I268: 0.053882961 | J268: 0.014566581 | K268: 0.083707129 | L268: 0.026112926 | M268: 0.0070559886 | N268: 0.019730064 | O268: 0.0037645747 | P268: 0.021251847 | Q268: 0.018089446 | R268: 0.0037024137 | S268: 0.052251742 | T268: 0.010673018 | U268: 0.00033107432 | V268: 0.01735256 | W268: 0.0059470165 | X268: 0.007751035 | Y268: 0.0028685912 | Z268: 0.47910782 | AA268: 0 | AB268: 0 | AC268: 0 | AD268: 0 | AE268: 0 | AF268: 0 | AG268: 0 | AH268: 0 | AI268: 0 | AJ268: 0 | AK268: 0 | AL268: 0 | AM268: 0 | AN268: 0 | AO268: 0 | AP268: 0 | AQ268: 0 | AR268: 0 | AS268: 0 | AT268: 0 | AU268: 0
A269: θ | B269: 0.00023262531 | C269: 0.0067372969 | D269: 0.0080129703 | E269: 0.0047156588 | F269: 0.034100615 | G269: 0.042531699 | H269: 0.032780763 | I269: 0.066221827 | J269: 0.017822673 | K269: 0.10241832 | L269: 0.031450773 | M269: 0.0086332253 | N269: 0.024140358 | O269: 0.0045341064 | P269: 0.026002307 | Q269: 0.02213301 | R269: 0.0047042519 | S269: 0.06393166 | T269: 0.013058776 | U269: 0.00040507991 | V269: 0.023885331 | W269: 0.0072763629 | X269: 0.010669091 | Y269: 0.0039485387 | Z269: 0.43965268 | AA269: 0 | AB269: 0 | AC269: 0 | AD269: 0 | AE269: 0 | AF269: 0 | AG269: 0 | AH269: 0 | AI269: 0 | AJ269: 0 | AK269: 0 | AL269: 0 | AM269: 0 | AN269: 0 | AO269: 0 | AP269: 0 | AQ269: 0 | AR269: 0 | AS269: 0 | AT269: 0 | AU269: 0
A270: ð | B270: 0.00027930349 | C270: 0.0045501698 | D270: 0.0054117217 | E270: 0.0031848156 | F270: 0.023030541 | G270: 0.028596978 | H270: 0.022139151 | I270: 0.079509779 | J270: 0.02106458 | K270: 0.12351837 | L270: 0.037761628 | M270: 0.010365553 | N270: 0.028531438 | O270: 0.005443912 | P270: 0.030732072 | Q270: 0.02657418 | R270: 0.0056481986 | S270: 0.075560696 | T270: 0.015679126 | U270: 0.00045596486 | V270: 0.028678119 | W270: 0.0098284779 | X270: 0.012809932 | Y270: 0.0047408453 | Z270: 0.39590445 | AA270: 0 | AB270: 0 | AC270: 0 | AD270: 0 | AE270: 0 | AF270: 0 | AG270: 0 | AH270: 0 | AI270: 0 | AJ270: 0 | AK270: 0 | AL270: 0 | AM270: 0 | AN270: 0 | AO270: 0 | AP270: 0 | AQ270: 0 | AR270: 0 | AS270: 0 | AT270: 0 | AU270: 0
A271: t | B271: 0.00022466324 | C271: 0.0065066993 | D271: 0.0043530245 | E271: 0.0015180853 | F271: 0.010585753 | G271: 0.013144309 | H271: 0.010130808 | I271: 0.03581494 | J271: 0.053789549 | K271: 0.098912846 | L271: 0.030374307 | M271: 0.026055424 | N271: 0.040799684 | O271: 0.0043789174 | P271: 0.025112325 | Q271: 0.021375463 | R271: 0.0045432394 | S271: 0.06174347 | T271: 0.012611813 | U271: 0.00039121523 | V271: 0.069203423 | W271: 0.022838773 | X271: 0.0171732 | Y271: 0.0038133919 | Z271: 0.42460468 | AA271: 0 | AB271: 0 | AC271: 0 | AD271: 0 | AE271: 0 | AF271: 0 | AG271: 0 | AH271: 0 | AI271: 0 | AJ271: 0 | AK271: 0 | AL271: 0 | AM271: 0 | AN271: 0 | AO271: 0 | AP271: 0 | AQ271: 0 | AR271: 0 | AS271: 0 | AT271: 0 | AU271: 0
A272: s | B272: 0.00025374279 | C272: 0.004133757 | D272: 0.0036873474 | E272: 0.0020896449 | F272: 0.015941242 | G272: 0.019484926 | H272: 0.015017757 | I272: 0.054175029 | J272: 0.025515782 | K272: 0.1496193 | L272: 0.045945321 | M272: 0.012359734 | N272: 0.034560478 | O272: 0.0066237156 | P272: 0.037226133 | Q272: 0.031686664 | R272: 0.0068417317 | S272: 0.091527591 | T272: 0.018695561 | U272: 0.00053850789 | V272: 0.03256702 | W272: 0.011905355 | X272: 0.014547025 | Y272: 0.0053837284 | Z272: 0.35967291 | AA272: 0 | AB272: 0 | AC272: 0 | AD272: 0 | AE272: 0 | AF272: 0 | AG272: 0 | AH272: 0 | AI272: 0 | AJ272: 0 | AK272: 0 | AL272: 0 | AM272: 0 | AN272: 0 | AO272: 0 | AP272: 0 | AQ272: 0 | AR272: 0 | AS272: 0 | AT272: 0 | AU272: 0
A273: ʧ | B273: 0.00020788062 | C273: 0.0032611804 | D273: 0.0029090014 | E273: 0.0031605355 | F273: 0.013059978 | G273: 0.01621655 | H273: 0.012303406 | I273: 0.044186027 | J273: 0.020903989 | K273: 0.1225767 | L273: 0.0669174 | M273: 0.010286529 | N273: 0.028313923 | O273: 0.0054024091 | P273: 0.054460321 | Q273: 0.046150275 | R273: 0.0098089921 | S273: 0.074984642 | T273: 0.015559593 | U273: 0.00081447968 | V273: 0.028459485 | W273: 0.0097535483 | X273: 0.012712272 | Y273: 0.0047047024 | Z273: 0.39288618 | AA273: 0 | AB273: 0 | AC273: 0 | AD273: 0 | AE273: 0 | AF273: 0 | AG273: 0 | AH273: 0 | AI273: 0 | AJ273: 0 | AK273: 0 | AL273: 0 | AM273: 0 | AN273: 0 | AO273: 0 | AP273: 0 | AQ273: 0 | AR273: 0 | AS273: 0 | AT273: 0 | AU273: 0
A274: d | B274: 0.00028895826 | C274: 0.004707457 | D274: 0.0030326781 | E274: 0.001098302 | F274: 0.0073749138 | G274: 0.0095096247 | H274: 0.0073294215 | I274: 0.02632263 | J274: 0.038915581 | K274: 0.071561316 | L274: 0.022323969 | M274: 0.033512069 | N274: 0.052710167 | O274: 0.0056320934 | P274: 0.031794397 | Q274: 0.027492778 | R274: 0.0058434417 | S274: 0.078172626 | T274: 0.016221111 | U274: 0.00061324424 | V274: 0.089008333 | W274: 0.030504666 | X274: 0.021535697 | Y274: 0.0049047236 | Z274: 0.4095898 | AA274: 0 | AB274: 0 | AC274: 0 | AD274: 0 | AE274: 0 | AF274: 0 | AG274: 0 | AH274: 0 | AI274: 0 | AJ274: 0 | AK274: 0 | AL274: 0 | AM274: 0 | AN274: 0 | AO274: 0 | AP274: 0 | AQ274: 0 | AR274: 0 | AS274: 0 | AT274: 0 | AU274: 0
... A307: jʊə | B307: 0 | C307: 0 | D307: 0 | E307: 0 | F307: 0 | G307: 0 | H307: 0 | I307: 0 | J307: 0 | K307: 0 | L307: 0 | M307: 0 | N307: 0 | O307: 0 | P307: 0 | Q307: 0 | R307: 0 | S307: 0 | T307: 0 | U307: 0 | V307: 0 | W307: 0 | X307: 0 | Y307: 0 | Z307: 0.50373807 | AA307: 0.007307223 | AB307: 0.0013760138 | AC307: 0.0010464446 | AD307: 0.016880285 | AE307: 0.0066311664 | AF307: 0.003539322 | AG307: 0.011864191 | AH307: 0.03720045 | AI307: 0.0075328548 | AJ307: 0.026808725 | AK307: 0.020760444 | AL307: 0.031721896 | AM307: 0.032020787 | AN307: 0.030877509 | AO307: 0.036204517 | AP307: 0.023723038 | AQ307: 0.082809847 | AR307: 0.0073077268 | AS307: 0.064781151 | AT307: 0.042302048 | AU307: 0.0035662926
A314: 0 | B314: 1 | C314: 2 | D314: 3 | E314: 4 | F314: 5 | G314: 6 | H314: 7 | I314: 8 | J314: 9 | K314: 10 | L314: 11 | M314: 12 | N314: 13 | O314: 14 | P314: 15 | Q314: 16 | R314: 17 | S314: 18 | T314: 19 | U314: 20 | V314: 21 | W314: 22 | X314: 23 | Y314: 24 | Z314: 25 | AA314: 26 | AB314: 27 | AC314: 28 | AD314: 29 | AE314: 30 | AF314: 31 | AG314: 32 | AH314: 33 | AI314: 34 | AJ314: 35 | AK314: 36 | AL314: 37 | AM314: 38 | AN314: 39 | AO314: 40 | AP314: 41 | AQ314: 42 | AR314: 43 | AS314: 44 | AT314: 45 | AU314: 46
...

Sheet Language Rules Dont Touch
B1: 1 | C1: 2 | D1: 3 | E1: 4 | F1: 5 | G1: 6 | H1: 7 | I1: 8 | J1: 9 | K1: 10 | L1: 11 | M1: 12 | N1: 13 | O1: 14 | P1: 15 | Q1: 16 | R1: 17 | S1: 18 | T1: 19 | U1: 20 | V1: 21 | W1: 22 | X1: 23 | Y1: 24 | Z1: 25 | AA1: 26 | AB1: 27 | AC1: 28 | AD1: 29 | AE1: 30 | AF1: 31 | AG1: 32 | AH1: 33 | AI1: 34 | AJ1: 35 | AK1: 36 | AL1: 37 | AM1: 38 | AN1: 39 | AO1: 40 | AP1: 41 | AQ1: 42 | AR1: 43 | AS1: 44 | AT1: 45 | AU1: 46
A2: conversion chart final | B2: p | C2: b | D2: m | E2: w | F2: f | G2: v | H2: θ | I2: ð | J2: t | K2: s | L2: ʧ | M2: d | N2: n | O2: z | P2: ʤ | Q2: r | R2: l | S2: ʃ | T2: ʒ | U2: jə | V2: k | W2: g | X2: ŋ | Y2: h | Z2: " | AA2: æ | AB2: ɛ | AC2: ɪ | AD2: ɒ | AE2: ʌ | AF2: ʊ | AG2: eɪ | AH2: i | AI2: aɪ | AJ2: əʊ | AK2: u | AL2: ɑ | AM2: ɜ | AN2: ɔ | AO2: ju | AP2: ɔɪ | AQ2: aʊ | AR2: ə | AS2: e | AT2: ɪə | AU2: jʊə
A3: p | B3: =IF(B263=0,1,SUM($B263:B263)) -> 0.013112396 | C3: =IF(C263=0,1,SUM($B263:C263)) -> 0.036485489 | D3: =IF(D263=0,1,SUM($B263:D263)) -> 0.069542935 | E3: =IF(E263=0,1,SUM($B263:E263)) -> 0.084576733 | F3: =IF(F263=0,1,SUM($B263:F263)) -> 0.098715663 | G3: =IF(G263=0,1,SUM($B263:G263)) -> 0.13463923 | H3: =IF(H263=0,1,SUM($B263:H263)) -> 0.15162126 | I3: =IF(I263=0,1,SUM($B263:I263)) -> 0.18892746 | ... AU3: =IF(AU263=0,1,SUM($B263:AU263)) -> 1
A4: b | B4: =IF(B264=0,1,SUM($B264:B264)) -> 0.0087448061 | C4: =IF(C264=0,1,SUM($B264:C264)) -> 0.036456418 | D4: =IF(D264=0,1,SUM($B264:D264)) -> 0.075824967 | E4: =IF(E264=0,1,SUM($B264:E264)) -> 0.093649342 | F4: =IF(F264=0,1,SUM($B264:F264)) -> 0.11015082 | G4: =IF(G264=0,1,SUM($B264:G264)) -> 0.15274252 | H4: =IF(H264=0,1,SUM($B264:H264)) -> 0.17287676 | I4: =IF(I264=0,1,SUM($B264:I264)) -> 0.21880895 | ... AU4: =IF(AU264=0,1,SUM($B264:AU264)) -> 1
A5: m | B5: =IF(B265=0,1,SUM($B265:B265)) -> 0.0060230888 | C5: =IF(C265=0,1,SUM($B265:C265)) -> 0.025194998 | D5: =IF(D265=0,1,SUM($B265:D265)) -> 0.073615631 | E5: =IF(E265=0,1,SUM($B265:E265)) -> 0.095195854 | F5: =IF(F265=0,1,SUM($B265:F265)) -> 0.11549154 | G5: =IF(G265=0,1,SUM($B265:G265)) -> 0.16705792 | H5: =IF(H265=0,1,SUM($B265:H265)) -> 0.19182167 | I5: =IF(I265=0,1,SUM($B265:I265)) -> 0.24831512 | ... AU5: =IF(AU265=0,1,SUM($B265:AU265)) -> 1
A6: w | B6: =IF(B266=0,1,SUM($B266:B266)) -> 0.0026411118 | C6: =IF(C266=0,1,SUM($B266:C266)) -> 0.01101059 | D6: =IF(D266=0,1,SUM($B266:D266)) -> 0.031818289 | E6: =IF(E266=0,1,SUM($B266:E266)) -> 0.08438986 | F6: =IF(F266=0,1,SUM($B266:F266)) -> 0.09996419 | G6: =IF(G266=0,1,SUM($B266:G266)) -> 0.14016286 | H6: =IF(H266=0,1,SUM($B266:H266)) -> 0.15916584 | I6: =IF(I266=0,1,SUM($B266:I266)) -> 0.2025173 | ... AU6: =IF(AU266=0,1,SUM($B266:AU266)) -> 1
A7: f | B7: =IF(B267=0,1,SUM($B267:B267)) -> 0.0027309776 | C7: =IF(C267=0,1,SUM($B267:C267)) -> 0.011250011 | D7: =IF(D267=0,1,SUM($B267:D267)) -> 0.032765707 | E7: =IF(E267=0,1,SUM($B267:E267)) -> 0.04988922 | F7: =IF(F267=0,1,SUM($B267:F267)) -> 0.078646824 | G7: =IF(G267=0,1,SUM($B267:G267)) -> 0.15171286 | H7: =IF(H267=0,1,SUM($B267:H267)) -> 0.18609962 | I7: =IF(I267=0,1,SUM($B267:I267)) -> 0.26454604 | ... AU7: =IF(AU267=0,1,SUM($B267:AU267)) -> 1
A8: v | B8: =IF(B268=0,1,SUM($B268:B268)) -> 0.0017514851 | C8: =IF(C268=0,1,SUM($B268:C268)) -> 0.0073018056 | D8: =IF(D268=0,1,SUM($B268:D268)) -> 0.021100682 | E8: =IF(E268=0,1,SUM($B268:E268)) -> 0.040624226 | F8: =IF(F268=0,1,SUM($B268:F268)) -> 0.059067627 | G8: =IF(G268=0,1,SUM($B268:G268)) -> 0.1423746 | H8: =IF(H268=0,1,SUM($B268:H268)) -> 0.18175604 | I8: =IF(I268=0,1,SUM($B268:I268)) -> 0.2711975 | ... AU8: =IF(AU268=0,1,SUM($B268:AU268)) -> 1
A9: θ | B9: =IF(B269=0,1,SUM($B269:B269)) -> 0.001545772 | C9: =IF(C269=0,1,SUM($B269:C269)) -> 0.0052195955 | D9: =IF(D269=0,1,SUM($B269:D269)) -> 0.014498215 | E9: =IF(E269=0,1,SUM($B269:E269)) -> 0.021882711 | F9: =IF(F269=0,1,SUM($B269:F269)) -> 0.034036362 | G9: =IF(G269=0,1,SUM($B269:G269)) -> 0.089178242 | H9: =IF(H269=0,1,SUM($B269:H269)) -> 0.13551966 | I9: =IF(I269=0,1,SUM($B269:I269)) -> 0.24123818 | ... AU9: =IF(AU269=0,1,SUM($B269:AU269)) -> 1
A10: ð | B10: =IF(B270=0,1,SUM($B270:B270)) -> 0.0017910165 | C10: =IF(C270=0,1,SUM($B270:C270)) -> 0.004185407 | D10: =IF(D270=0,1,SUM($B270:D270)) -> 0.010232687 | E10: =IF(E270=0,1,SUM($B270:E270)) -> 0.015045484 | F10: =IF(F270=0,1,SUM($B270:F270)) -> 0.022966546 | G10: =IF(G270=0,1,SUM($B270:G270)) -> 0.05874518 | H10: =IF(H270=0,1,SUM($B270:H270)) -> 0.088947895 | I10: =IF(I270=0,1,SUM($B270:I270)) -> 0.2114392 | ... AU10: =IF(AU270=0,1,SUM($B270:AU270)) -> 1
A11: t | B11: =IF(B271=0,1,SUM($B271:B271)) -> 0.0016592917 | C11: =IF(C271=0,1,SUM($B271:C271)) -> 0.0056029168 | D11: =IF(D271=0,1,SUM($B271:D271)) -> 0.011205434 | E11: =IF(E271=0,1,SUM($B271:E271)) -> 0.013847703 | F11: =IF(F271=0,1,SUM($B271:F271)) -> 0.018041124 | G11: =IF(G271=0,1,SUM($B271:G271)) -> 0.036982384 | H11: =IF(H271=0,1,SUM($B271:H271)) -> 0.052900681 | I11: =IF(I271=0,1,SUM($B271:I271)) -> 0.11645081 | ... AU11: =IF(AU271=0,1,SUM($B271:AU271)) -> 1
A12: s | B12: =IF(B272=0,1,SUM($B272:B272)) -> 0.0015962864 | C12: =IF(C272=0,1,SUM($B272:C272)) -> 0.0037303445 | D12: =IF(D272=0,1,SUM($B272:D272)) -> 0.007772682 | E12: =IF(E272=0,1,SUM($B272:E272)) -> 0.010870669 | F12: =IF(F272=0,1,SUM($B272:F272)) -> 0.016249593 | G12: =IF(G272=0,1,SUM($B272:G272)) -> 0.040166018 | H12: =IF(H272=0,1,SUM($B272:H272)) -> 0.060265459 | I12: =IF(I272=0,1,SUM($B272:I272)) -> 0.14214545 | ... AU12: =IF(AU272=0,1,SUM($B272:AU272)) -> 1
A13: ʧ | B13: =IF(B273=0,1,SUM($B273:B273)) -> 0.0011992546 | C13: =IF(C273=0,1,SUM($B273:C273)) -> 0.0027431447 | D13: =IF(D273=0,1,SUM($B273:D273)) -> 0.0056675848 | E13: =IF(E273=0,1,SUM($B273:E273)) -> 0.0099644139 | F13: =IF(F273=0,1,SUM($B273:F273)) -> 0.01400548 | G13: =IF(G273=0,1,SUM($B273:G273)) -> 0.032258564 | H13: =IF(H273=0,1,SUM($B273:H273)) -> 0.047358829 | I13: =IF(I273=0,1,SUM($B273:I273)) -> 0.10860005 | ... AU13: =IF(AU273=0,1,SUM($B273:AU273)) -> 1
A14: d | B14: =IF(B274=0,1,SUM($B274:B274)) -> 0.0020678131 | C14: =IF(C274=0,1,SUM($B274:C274)) -> 0.0048322499 | D14: =IF(D274=0,1,SUM($B274:D274)) -> 0.0086140961 | E14: =IF(E274=0,1,SUM($B274:E274)) -> 0.010466296 | F14: =IF(F274=0,1,SUM($B274:F274)) -> 0.013296966 | G14: =IF(G274=0,1,SUM($B274:G274)) -> 0.026574577 | H14: =IF(H274=0,1,SUM($B274:H274)) -> 0.037733124 | I14: =IF(I274=0,1,SUM($B274:I274)) -> 0.082988161 | ... AU14: =IF(AU274=0,1,SUM($B274:AU274)) -> 1
... A26: h | B26: =IF(B286=0,1,SUM($B286:B286)) -> 0.00066074394 | C26: =IF(C286=0,1,SUM($B286:C286)) -> 0.00085704203 | D26: =IF(D286=0,1,SUM($B286:D286)) -> 0.0016006986 | E26: =IF(E286=0,1,SUM($B286:E286)) -> 0.0019952636 | F26: =IF(F286=0,1,SUM($B286:F286)) -> 0.0028301916 | G26: =IF(G286=0,1,SUM($B286:G286)) -> 0.0066014762 | H26: =IF(H286=0,1,SUM($B286:H286)) -> 0.010167051 | I26: =IF(I286=0,1,SUM($B286:I286)) -> 0.024627735 | ... AU26: =IF(AU286=0,1,SUM($B286:AU286)) -> 1
A27: æ | B27: =IF(B287=0,0,SUM($B287:B287)) -> 0 | C27: =IF(C287=0,0,SUM($B287:C287)) -> 0 | D27: =IF(D287=0,0,SUM($B287:D287)) -> 0 | E27: =IF(E287=0,0,SUM($B287:E287)) -> 0 | F27: =IF(F287=0,0,SUM($B287:F287)) -> 0 | G27: =IF(G287=0,0,SUM($B287:G287)) -> 0 | H27: =IF(H287=0,0,SUM($B287:H287)) -> 0 | I27: =IF(I287=0,0,SUM($B287:I287)) -> 0 | ... AU27: =IF(AU287=0,0,SUM($B287:AU287)) -> 1
A28: ɛ | B28: =IF(B288=0,0,SUM($B288:B288)) -> 0 | C28: =IF(C288=0,0,SUM($B288:C288)) -> 0 | D28: =IF(D288=0,0,SUM($B288:D288)) -> 0 | E28: =IF(E288=0,0,SUM($B288:E288)) -> 0 | F28: =IF(F288=0,0,SUM($B288:F288)) -> 0 | G28: =IF(G288=0,0,SUM($B288:G288)) -> 0 | H28: =IF(H288=0,0,SUM($B288:H288)) -> 0 | I28: =IF(I288=0,0,SUM($B288:I288)) -> 0 | ... AU28: =IF(AU288=0,0,SUM($B288:AU288)) -> 1
A29: ɪ | B29: =IF(B289=0,0,SUM($B289:B289)) -> 0 | C29: =IF(C289=0,0,SUM($B289:C289)) -> 0 | D29: =IF(D289=0,0,SUM($B289:D289)) -> 0 | E29: =IF(E289=0,0,SUM($B289:E289)) -> 0 | F29: =IF(F289=0,0,SUM($B289:F289)) -> 0 | G29: =IF(G289=0,0,SUM($B289:G289)) -> 0 | H29: =IF(H289=0,0,SUM($B289:H289)) -> 0 | I29: =IF(I289=0,0,SUM($B289:I289)) -> 0 | ... AU29: =IF(AU289=0,0,SUM($B289:AU289)) -> 1
A30: ɒ | B30: =IF(B290=0,0,SUM($B290:B290)) -> 0 | C30: =IF(C290=0,0,SUM($B290:C290)) -> 0 | D30: =IF(D290=0,0,SUM($B290:D290)) -> 0 | E30: =IF(E290=0,0,SUM($B290:E290)) -> 0 | F30: =IF(F290=0,0,SUM($B290:F290)) -> 0 | G30: =IF(G290=0,0,SUM($B290:G290)) -> 0 | H30: =IF(H290=0,0,SUM($B290:H290)) -> 0 | I30: =IF(I290=0,0,SUM($B290:I290)) -> 0 | ... AU30: =IF(AU290=0,0,SUM($B290:AU290)) -> 1
A31: ʌ | B31: =IF(B291=0,0,SUM($B291:B291)) -> 0 | C31: =IF(C291=0,0,SUM($B291:C291)) -> 0 | D31: =IF(D291=0,0,SUM($B291:D291)) -> 0 | E31: =IF(E291=0,0,SUM($B291:E291)) -> 0 | F31: =IF(F291=0,0,SUM($B291:F291)) -> 0 | G31: =IF(G291=0,0,SUM($B291:G291)) -> 0 | H31: =IF(H291=0,0,SUM($B291:H291)) -> 0 | I31: =IF(I291=0,0,SUM($B291:I291)) -> 0 | ... AU31: =IF(AU291=0,0,SUM($B291:AU291)) -> 1
A32: ʊ | B32: =IF(B292=0,0,SUM($B292:B292)) -> 0 | C32: =IF(C292=0,0,SUM($B292:C292)) -> 0 | D32: =IF(D292=0,0,SUM($B292:D292)) -> 0 | E32: =IF(E292=0,0,SUM($B292:E292)) -> 0 | F32: =IF(F292=0,0,SUM($B292:F292)) -> 0 | G32: =IF(G292=0,0,SUM($B292:G292)) -> 0 | H32: =IF(H292=0,0,SUM($B292:H292)) -> 0 | I32: =IF(I292=0,0,SUM($B292:I292)) -> 0 | ... AU32: =IF(AU292=0,0,SUM($B292:AU292)) -> 1
A33: eɪ | B33: =IF(B293=0,0,SUM($B293:B293)) -> 0 | C33: =IF(C293=0,0,SUM($B293:C293)) -> 0 | D33: =IF(D293=0,0,SUM($B293:D293)) -> 0 | E33: =IF(E293=0,0,SUM($B293:E293)) -> 0 | F33: =IF(F293=0,0,SUM($B293:F293)) -> 0 | G33: =IF(G293=0,0,SUM($B293:G293)) -> 0 | H33: =IF(H293=0,0,SUM($B293:H293)) -> 0 | I33: =IF(I293=0,0,SUM($B293:I293)) -> 0 | ... AU33: =IF(AU293=0,0,SUM($B293:AU293)) -> 1
A34: i | B34: =IF(B294=0,0,SUM($B294:B294)) -> 0 | C34: =IF(C294=0,0,SUM($B294:C294)) -> 0 | D34: =IF(D294=0,0,SUM($B294:D294)) -> 0 | E34: =IF(E294=0,0,SUM($B294:E294)) -> 0 | F34: =IF(F294=0,0,SUM($B294:F294)) -> 0 | G34: =IF(G294=0,0,SUM($B294:G294)) -> 0 | H34: =IF(H294=0,0,SUM($B294:H294)) -> 0 | I34: =IF(I294=0,0,SUM($B294:I294)) -> 0 | ... AU34: =IF(AU294=0,0,SUM($B294:AU294)) -> 1
A35: aɪ | B35: =IF(B295=0,0,SUM($B295:B295)) -> 0 | C35: =IF(C295=0,0,SUM($B295:C295)) -> 0 | D35: =IF(D295=0,0,SUM($B295:D295)) -> 0 | E35: =IF(E295=0,0,SUM($B295:E295)) -> 0 | F35: =IF(F295=0,0,SUM($B295:F295)) -> 0 | G35: =IF(G295=0,0,SUM($B295:G295)) -> 0 | H35: =IF(H295=0,0,SUM($B295:H295)) -> 0 | I35: =IF(I295=0,0,SUM($B295:I295)) -> 0 | ... AU35: =IF(AU295=0,0,SUM($B295:AU295)) -> 1
A36: əʊ | B36: =IF(B296=0,0,SUM($B296:B296)) -> 0 | C36: =IF(C296=0,0,SUM($B296:C296)) -> 0 | D36: =IF(D296=0,0,SUM($B296:D296)) -> 0 | E36: =IF(E296=0,0,SUM($B296:E296)) -> 0 | F36: =IF(F296=0,0,SUM($B296:F296)) -> 0 | G36: =IF(G296=0,0,SUM($B296:G296)) -> 0 | H36: =IF(H296=0,0,SUM($B296:H296)) -> 0 | I36: =IF(I296=0,0,SUM($B296:I296)) -> 0 | ... AU36: =IF(AU296=0,0,SUM($B296:AU296)) -> 1
A37: u | B37: =IF(B297=0,0,SUM($B297:B297)) -> 0 | C37: =IF(C297=0,0,SUM($B297:C297)) -> 0 | D37: =IF(D297=0,0,SUM($B297:D297)) -> 0 | E37: =IF(E297=0,0,SUM($B297:E297)) -> 0 | F37: =IF(F297=0,0,SUM($B297:F297)) -> 0 | G37: =IF(G297=0,0,SUM($B297:G297)) -> 0 | H37: =IF(H297=0,0,SUM($B297:H297)) -> 0 | I37: =IF(I297=0,0,SUM($B297:I297)) -> 0 | ... AU37: =IF(AU297=0,0,SUM($B297:AU297)) -> 1
A38: ɑ | B38: =IF(B298=0,0,SUM($B298:B298)) -> 0 | C38: =IF(C298=0,0,SUM($B298:C298)) -> 0 | D38: =IF(D298=0,0,SUM($B298:D298)) -> 0 | E38: =IF(E298=0,0,SUM($B298:E298)) -> 0 | F38: =IF(F298=0,0,SUM($B298:F298)) -> 0 | G38: =IF(G298=0,0,SUM($B298:G298)) -> 0 | H38: =IF(H298=0,0,SUM($B298:H298)) -> 0 | I38: =IF(I298=0,0,SUM($B298:I298)) -> 0 | ... AU38: =IF(AU298=0,0,SUM($B298:AU298)) -> 1
... A47: jʊə | B47: =IF(B307=0,0,SUM($B307:B307)) -> 0 | C47: =IF(C307=0,0,SUM($B307:C307)) -> 0 | D47: =IF(D307=0,0,SUM($B307:D307)) -> 0 | E47: =IF(E307=0,0,SUM($B307:E307)) -> 0 | F47: =IF(F307=0,0,SUM($B307:F307)) -> 0 | G47: =IF(G307=0,0,SUM($B307:G307)) -> 0 | H47: =IF(H307=0,0,SUM($B307:H307)) -> 0 | I47: =IF(I307=0,0,SUM($B307:I307)) -> 0 | ... AU47: =IF(AU307=0,0,SUM($B307:AU307)) -> 1
A51: Short | B51: æ | C51: ɛ | D51: ɪ | E51: ɒ | F51: ʌ | G51: ʊ
A52: Long | B52: eɪ | C52: i | D52: aɪ | E52: əʊ | G52: u
A53: R | B53: ɑ | C53: ɜ | D53: ɔ
A54: Other | B54: ju | C54: ɔɪ | D54: aʊ | E54: ə | F54: e | G54: ɪə | H54: jʊə
B57: 0.0625 | C57: 0.125 | D57: 0.1875 | E57: 0.25 | F57: 0.3125 | G57: 0.375 | H57: 0.4375 | I57: 0.5 | J57: 0.5625 | K57: 0.625 | L57: 0.6875 | M57: 0.75 | N57: 0.8125 | O57: 0.875 | P57: 0.9375 | Q57: 1 | V57: 0.14285714 | W57: 0.28571429 | X57: 0.42857143 | Y57: 0.57142857 | Z57: 0.71428571 | AA57: 0.85714286 | AB57: 1
B58: 1 | C58: 0.9375 | D58: 0.875 | E58: 0.8125 | F58: 0.75 | G58: 0.6875 | H58: 0.625 | I58: 0.5625 | J58: 0.5 | K58: 0.4375 | L58: 0.375 | M58: 0.3125 | N58: 0.25 | O58: 0.1875 | P58: 0.125 | Q58: 0.0625 | V58: 1 | W58: 0.85714286 | X58: 0.71428571 | Y58: 0.57142857 | Z58: 0.42857143 | AA58: 0.28571429 | AB58: 0.14285714
B59: Bilabial | D59: Labio-dental | F59: Inter-dental | H59: Alveolar | J59: Post-alveolar | L59: Palatal | N59: Velar | P59: Glottal | U59: Short | V59: æ | W59: ɛ | X59: ɪ | Y59: ɒ | Z59: ʌ | AA59: ʊ | AC59: =1/4 -> 0.25 | AD59: =4/4 -> 1
A60: Stops | B60: p | C60: b | H60: t | I60: d | N60: k | O60: g | R60: 0.16666667 | S60: 1 | U60: Long | V60: eɪ | W60: i | X60: aɪ | Y60: əʊ | AA60: u | AC60: =2/4 -> 0.5 | AD60: =3/4 -> 0.75
A61: Nasal | C61: m | I61: n | O61: ŋ | R61: 0.33333333 | S61: 0.83333333 | U61: R | V61: ɑ | W61: ɜ | X61: ɔ | AC61: =3/4 -> 0.75 | AD61: =2/4 -> 0.5
A62: Fricative | D62: f | E62: v | F62: θ | G62: ð | H62: s | I62: z | J62: ʃ | K62: ʒ | P62: h | R62: 0.5 | S62: 0.66666667 | U62: Other | V62: ju | W62: ɔɪ | X62: aʊ | Y62: ə | Z62: e | AA62: ɪə | AB62: jʊə | AC62: =4/4 -> 1 | AD62: =1/4 -> 0.25
A63: Affricates | H63: ʧ | I63: ʤ | R63: 0.66666667 | S63: 0.5
A64: Approximants | C64: w | I64: r | M64: jə | R64: 0.83333333 | S64: 0.33333333
A65: Lateral | I65: l | R65: 1 | S65: 0.16666667
A68: 1 | B68: 0.0625 | C68: 0.125 | D68: 0.1875 | E68: 0.25 | F68: 0.3125 | G68: 0.375 | H68: 0.4375 | I68: 0.5 | J68: 0.5625 | K68: 0.625 | L68: 0.6875 | M68: 0.75 | N68: 0.8125 | O68: 0.875 | P68: 0.9375 | Q68: 1 | U68: 1 | V68: 0.14285714 | W68: 0.28571429 | X68: 0.42857143 | Y68: 0.57142857 | Z68: 0.71428571 | AA68: 0.85714286 | AB68: 1
A69: 1 | B69: 1 | C69: 0.9375 | D69: 0.875 | E69: 0.8125 | F69: 0.75 | G69: 0.6875 | H69: 0.625 | I69: 0.5625 | J69: 0.5 | K69: 0.4375 | L69: 0.375 | M69: 0.3125 | N69: 0.25 | O69: 0.1875 | P69: 0.125 | Q69: 0.0625 | U69: 1 | V69: 1 | W69: 0.85714286 | X69: 0.71428571 | Y69: 0.57142857 | Z69: 0.42857143 | AA69: 0.28571429 | AB69: 0.14285714
B70: Bilabial | D70: Labio-dental | F70: Inter-dental | H70: Alveolar | J70: Post-alveolar | L70: Palatal | N70: Velar | P70: Glottal | U70: Short | V70: =INDEX(V$68:V$69,$U$68,1)*INDEX($AC70:$AD70,1,$U$69) -> 0.035714286 | W70: =INDEX(W$68:W$69,$U$68,1)*INDEX($AC70:$AD70,1,$U$69) -> 0.071428571 | X70: =INDEX(X$68:X$69,$U$68,1)*INDEX($AC70:$AD70,1,$U$69) -> 0.10714286 | Y70: =INDEX(Y$68:Y$69,$U$68,1)*INDEX($AC70:$AD70,1,$U$69) -> 0.14285714 | Z70: =INDEX(Z$68:Z$69,$U$68,1)*INDEX($AC70:$AD70,1,$U$69) -> 0.17857143 | AA70: =INDEX(AA$68:AA$69,$U$68,1)*INDEX($AC70:$AD70,1,$U$69) -> 0.21428571 | AC70: =1/4 -> 0.25 | AD70: =4/4 -> 1
A71: Stops | B71: {=INDEX(B$68:B$69,$A$68,1)*INDEX($R71:$S71,1,$A$69)} -> 0.010416667 | C71: {=INDEX(C$68:C$69,$A$68,1)*_xlfn.SINGLE(INDEX($R71:$S71,1,$A$69))} -> 0.020833333 | H71: {=INDEX(H$68:H$69,$A$68,1)*_xlfn.SINGLE(INDEX($R71:$S71,1,$A$69))} -> 0.072916667 | I71: {=INDEX(I$68:I$69,$A$68,1)*_xlfn.SINGLE(INDEX($R71:$S71,1,$A$69))} -> 0.083333333 | N71: {=INDEX(N$68:N$69,$A$68,1)*_xlfn.SINGLE(INDEX($R71:$S71,1,$A$69))} -> 0.13541667 | O71: {=INDEX(O$68:O$69,$A$68,1)*_xlfn.SINGLE(INDEX($R71:$S71,1,$A$69))} -> 0.14583333 | R71: 0.16666667 | S71: 1 | U71: Long | V71: =INDEX(V$68:V$69,$U$68,1)*INDEX($AC71:$AD71,1,$U$69) -> 0.071428571 | W71: =INDEX(W$68:W$69,$U$68,1)*INDEX($AC71:$AD71,1,$U$69) -> 0.14285714 | X71: =INDEX(X$68:X$69,$U$68,1)*INDEX($AC71:$AD71,1,$U$69) -> 0.21428571 | Y71: =INDEX(Y$68:Y$69,$U$68,1)*INDEX($AC71:$AD71,1,$U$69) -> 0.28571429 | AA71: {=INDEX(AA$68:AA$69,$U$68,1)*INDEX($AC71:$AD71,1,$U$69)} -> 0.42857143 | AC71: =2/4 -> 0.5 | AD71: =3/4 -> 0.75
A72: Nasal | C72: {=INDEX(C$68:C$69,$A$68,1)*_xlfn.SINGLE(INDEX($R72:$S72,1,$A$69))} -> 0.041666667 | I72: {=INDEX(I$68:I$69,$A$68,1)*_xlfn.SINGLE(INDEX($R72:$S72,1,$A$69))} -> 0.16666667 | O72: {=INDEX(O$68:O$69,$A$68,1)*_xlfn.SINGLE(INDEX($R72:$S72,1,$A$69))} -> 0.29166667 | R72: 0.33333333 | S72: 0.83333333 | U72: R | V72: =INDEX(V$68:V$69,$U$68,1)*INDEX($AC72:$AD72,1,$U$69) -> 0.10714286 | W72: =INDEX(W$68:W$69,$U$68,1)*INDEX($AC72:$AD72,1,$U$69) -> 0.21428571 | X72: =INDEX(X$68:X$69,$U$68,1)*INDEX($AC72:$AD72,1,$U$69) -> 0.32142857 | AC72: =3/4 -> 0.75 | AD72: =2/4 -> 0.5
A73: Fricative | D73: {=INDEX(D$68:D$69,$A$68,1)*_xlfn.SINGLE(INDEX($R73:$S73,1,$A$69))} -> 0.09375 | E73: {=INDEX(E$68:E$69,$A$68,1)*_xlfn.SINGLE(INDEX($R73:$S73,1,$A$69))} -> 0.125 | F73: {=INDEX(F$68:F$69,$A$68,1)*_xlfn.SINGLE(INDEX($R73:$S73,1,$A$69))} -> 0.15625 | G73: {=INDEX(G$68:G$69,$A$68,1)*_xlfn.SINGLE(INDEX($R73:$S73,1,$A$69))} -> 0.1875 | H73: {=INDEX(H$68:H$69,$A$68,1)*_xlfn.SINGLE(INDEX($R73:$S73,1,$A$69))} -> 0.21875 | I73: {=INDEX(I$68:I$69,$A$68,1)*_xlfn.SINGLE(INDEX($R73:$S73,1,$A$69))} -> 0.25 | J73: {=INDEX(J$68:J$69,$A$68,1)*_xlfn.SINGLE(INDEX($R73:$S73,1,$A$69))} -> 0.28125 | K73: {=INDEX(K$68:K$69,$A$68,1)*_xlfn.SINGLE(INDEX($R73:$S73,1,$A$69))} -> 0.3125 | P73: {=INDEX(P$68:P$69,$A$68,1)*_xlfn.SINGLE(INDEX($R73:$S73,1,$A$69))} -> 0.46875 | R73: 0.5 | S73: 0.66666667 | U73: Other | V73: =INDEX(V$68:V$69,$U$68,1)*INDEX($AC73:$AD73,1,$U$69) -> 0.14285714 | W73: =INDEX(W$68:W$69,$U$68,1)*INDEX($AC73:$AD73,1,$U$69) -> 0.28571429 | X73: =INDEX(X$68:X$69,$U$68,1)*INDEX($AC73:$AD73,1,$U$69) -> 0.42857143 | Y73: =INDEX(Y$68:Y$69,$U$68,1)*INDEX($AC73:$AD73,1,$U$69) -> 0.57142857 | Z73: =INDEX(Z$68:Z$69,$U$68,1)*INDEX($AC73:$AD73,1,$U$69) -> 0.71428571 | AA73: =INDEX(AA$68:AA$69,$U$68,1)*INDEX($AC73:$AD73,1,$U$69) -> 0.85714286 | AB73: =INDEX(AB$68:AB$69,$U$68,1)*INDEX($AC73:$AD73,1,$U$69) -> 1 | AC73: =4/4 -> 1 | AD73: =1/4 -> 0.25
A74: Affricates | H74: {=INDEX(H$68:H$69,$A$68,1)*_xlfn.SINGLE(INDEX($R74:$S74,1,$A$69))} -> 0.29166667 | I74: {=INDEX(I$68:I$69,$A$68,1)*_xlfn.SINGLE(INDEX($R74:$S74,1,$A$69))} -> 0.33333333 | R74: 0.66666667 | S74: 0.5
A75: Approximants | C75: {=INDEX(C$68:C$69,$A$68,1)*_xlfn.SINGLE(INDEX($R75:$S75,1,$A$69))} -> 0.10416667 | I75: {=INDEX(I$68:I$69,$A$68,1)*_xlfn.SINGLE(INDEX($R75:$S75,1,$A$69))} -> 0.41666667 | M75: {=INDEX(M$68:M$69,$A$68,1)*_xlfn.SINGLE(INDEX($R75:$S75,1,$A$69))} -> 0.625 | R75: 0.83333333 | S75: 0.33333333
A76: Lateral | I76: {=INDEX(I$68:I$69,$A$68,1)*_xlfn.SINGLE(INDEX($R76:$S76,1,$A$69))} -> 0.5 | R76: 1 | S76: 0.16666667
A81: 1 | B81: 2 | C81: 3 | D81: 4 | E81: 5 | F81: 6 | G81: 7 | H81: 8 | I81: 9 | J81: 10 | K81: 11 | L81: 12 | M81: 13 | N81: 14 | O81: 15 | P81: 16 | Q81: 17 | R81: 18 | S81: 19 | T81: 20 | U81: 21 | V81: 22 | W81: 23 | X81: 24 | Y81: 25
A82: conversion chart 1 | B82: p | C82: b | D82: m | E82: w | F82: f | G82: v | H82: θ | I82: ð | J82: t | K82: s | L82: ʧ | M82: d | N82: n | O82: z | P82: ʤ | Q82: r | R82: l | S82: ʃ | T82: ʒ | U82: jə | V82: k | W82: g | X82: ŋ | Y82: h | Z82: æ | AA82: ɛ | AB82: ɪ | AC82: ɒ | AD82: ʌ | AE82: ʊ | AF82: eɪ | AG82: i | AH82: aɪ | AI82: əʊ | AJ82: u | AK82: ɑ | AL82: ɜ | AM82: ɔ | AN82: ju | AO82: ɔɪ | AP82: aʊ | AQ82: ə | AR82: e | AS82: ɪə | AT82: jʊə | AU82: 1
A83: p | B83: 0 | C83: 1 | D83: 2 | E83: 5 | F83: 4 | G83: 5 | H83: 6 | I83: 7 | J83: 6 | K83: 7 | L83: 8 | M83: 7 | N83: 8 | O83: 9 | P83: 10 | Q83: 11 | R83: 12 | S83: 10 | T83: 11 | U83: 15 | V83: 12 | W83: 13 | X83: 14 | Y83: 16 | Z83: 100 | AA83: 100 | AB83: 100 | AC83: 100 | AD83: 100 | AE83: 100 | AF83: 100 | AG83: 100 | AH83: 100 | AI83: 100 | AJ83: 100 | AK83: 100 | AL83: 100 | AM83: 100 | AN83: 100 | AO83: 100 | AP83: 100 | AQ83: 100 | AR83: 100 | AS83: 100 | AT83: 100 | AU83: 2
A84: b | B84: 1 | C84: 0 | D84: 1 | E84: 4 | F84: 3 | G84: 4 | H84: 5 | I84: 6 | J84: 5 | K84: 6 | L84: 7 | M84: 6 | N84: 7 | O84: 8 | P84: 9 | Q84: 10 | R84: 11 | S84: 9 | T84: 10 | U84: 14 | V84: 11 | W84: 12 | X84: 13 | Y84: 15 | Z84: 100 | AA84: 100 | AB84: 100 | AC84: 100 | AD84: 100 | AE84: 100 | AF84: 100 | AG84: 100 | AH84: 100 | AI84: 100 | AJ84: 100 | AK84: 100 | AL84: 100 | AM84: 100 | AN84: 100 | AO84: 100 | AP84: 100 | AQ84: 100 | AR84: 100 | AS84: 100 | AT84: 100 | AU84: 3
A85: m | B85: 2 | C85: 1 | D85: 0 | E85: 3 | F85: 2 | G85: 3 | H85: 4 | I85: 5 | J85: 6 | K85: 6 | L85: 7 | M85: 7 | N85: 6 | O85: 7 | P85: 8 | Q85: 9 | R85: 10 | S85: 8 | T85: 9 | U85: 13 | V85: 12 | W85: 13 | X85: 12 | Y85: 14 | Z85: 100 | AA85: 100 | AB85: 100 | AC85: 100 | AD85: 100 | AE85: 100 | AF85: 100 | AG85: 100 | AH85: 100 | AI85: 100 | AJ85: 100 | AK85: 100 | AL85: 100 | AM85: 100 | AN85: 100 | AO85: 100 | AP85: 100 | AQ85: 100 | AR85: 100 | AS85: 100 | AT85: 100 | AU85: 4
A86: w | B86: 5 | C86: 4 | D86: 3 | E86: 0 | F86: 3 | G86: 4 | H86: 5 | I86: 6 | J86: 9 | K86: 7 | L86: 6 | M86: 10 | N86: 9 | O86: 8 | P86: 7 | Q86: 6 | R86: 7 | S86: 9 | T86: 10 | U86: 10 | V86: 15 | W86: 16 | X86: 15 | Y86: 15 | Z86: 100 | AA86: 100 | AB86: 100 | AC86: 100 | AD86: 100 | AE86: 100 | AF86: 100 | AG86: 100 | AH86: 100 | AI86: 100 | AJ86: 100 | AK86: 100 | AL86: 100 | AM86: 100 | AN86: 100 | AO86: 100 | AP86: 100 | AQ86: 100 | AR86: 100 | AS86: 100 | AT86: 100 | AU86: 5
A87: f | B87: 4 | C87: 3 | D87: 2 | E87: 3 | F87: 0 | G87: 1 | H87: 2 | I87: 3 | J87: 6 | K87: 4 | L87: 5 | M87: 7 | N87: 6 | O87: 5 | P87: 6 | Q87: 7 | R87: 8 | S87: 6 | T87: 7 | U87: 11 | V87: 12 | W87: 13 | X87: 12 | Y87: 12 | Z87: 100 | AA87: 100 | AB87: 100 | AC87: 100 | AD87: 100 | AE87: 100 | AF87: 100 | AG87: 100 | AH87: 100 | AI87: 100 | AJ87: 100 | AK87: 100 | AL87: 100 | AM87: 100 | AN87: 100 | AO87: 100 | AP87: 100 | AQ87: 100 | AR87: 100 | AS87: 100 | AT87: 100 | AU87: 6
A88: v | B88: 5 | C88: 4 | D88: 3 | E88: 2 | F88: 1 | G88: 0 | H88: 1 | I88: 2 | J88: 5 | K88: 3 | L88: 4 | M88: 6 | N88: 5 | O88: 4 | P88: 5 | Q88: 6 | R88: 7 | S88: 5 | T88: 6 | U88: 10 | V88: 11 | W88: 12 | X88: 11 | Y88: 11 | Z88: 100 | AA88: 100 | AB88: 100 | AC88: 100 | AD88: 100 | AE88: 100 | AF88: 100 | AG88: 100 | AH88: 100 | AI88: 100 | AJ88: 100 | AK88: 100 | AL88: 100 | AM88: 100 | AN88: 100 | AO88: 100 | AP88: 100 | AQ88: 100 | AR88: 100 | AS88: 100 | AT88: 100 | AU88: 7
A89: θ | B89: 5 | C89: 5 | D89: 4 | E89: 5 | F89: 2 | G89: 1 | H89: 0 | I89: 1 | J89: 4 | K89: 2 | L89: 3 | M89: 5 | N89: 4 | O89: 3 | P89: 4 | Q89: 5 | R89: 6 | S89: 4 | T89: 5 | U89: 9 | V89: 10 | W89: 11 | X89: 10 | Y89: 10 | Z89: 100 | AA89: 100 | AB89: 100 | AC89: 100 | AD89: 100 | AE89: 100 | AF89: 100 | AG89: 100 | AH89: 100 | AI89: 100 | AJ89: 100 | AK89: 100 | AL89: 100 | AM89: 100 | AN89: 100 | AO89: 100 | AP89: 100 | AQ89: 100 | AR89: 100 | AS89: 100 | AT89: 100 | AU89: 8
A90: ð | B90: 4 | C90: 6 | D90: 5 | E90: 6 | F90: 3 | G90: 2 | H90: 1 | I90: 0 | J90: 3 | K90: 1 | L90: 2 | M90: 4 | N90: 3 | O90: 2 | P90: 3 | Q90: 4 | R90: 5 | S90: 3 | T90: 4 | U90: 8 | V90: 9 | W90: 10 | X90: 9 | Y90: 9 | Z90: 100 | AA90: 100 | AB90: 100 | AC90: 100 | AD90: 100 | AE90: 100 | AF90: 100 | AG90: 100 | AH90: 100 | AI90: 100 | AJ90: 100 | AK90: 100 | AL90: 100 | AM90: 100 | AN90: 100 | AO90: 100 | AP90: 100 | AQ90: 100 | AR90: 100 | AS90: 100 | AT90: 100 | AU90: 9
A91: t | B91: 5 | C91: 5 | D91: 6 | E91: 9 | F91: 6 | G91: 5 | H91: 4 | I91: 3 | J91: 0 | K91: 2 | L91: 3 | M91: 1 | N91: 2 | O91: 3 | P91: 4 | Q91: 5 | R91: 6 | S91: 4 | T91: 5 | U91: 9 | V91: 6 | W91: 7 | X91: 8 | Y91: 10 | Z91: 100 | AA91: 100 | AB91: 100 | AC91: 100 | AD91: 100 | AE91: 100 | AF91: 100 | AG91: 100 | AH91: 100 | AI91: 100 | AJ91: 100 | AK91: 100 | AL91: 100 | AM91: 100 | AN91: 100 | AO91: 100 | AP91: 100 | AQ91: 100 | AR91: 100 | AS91: 100 | AT91: 100 | AU91: 10
A92: s | B92: 4 | C92: 6 | D92: 6 | E92: 7 | F92: 4 | G92: 3 | H92: 2 | I92: 1 | J92: 2 | K92: 0 | L92: 1 | M92: 3 | N92: 2 | O92: 1 | P92: 2 | Q92: 3 | R92: 4 | S92: 2 | T92: 3 | U92: 7 | V92: 8 | W92: 9 | X92: 8 | Y92: 8 | Z92: 100 | AA92: 100 | AB92: 100 | AC92: 100 | AD92: 100 | AE92: 100 | AF92: 100 | AG92: 100 | AH92: 100 | AI92: 100 | AJ92: 100 | AK92: 100 | AL92: 100 | AM92: 100 | AN92: 100 | AO92: 100 | AP92: 100 | AQ92: 100 | AR92: 100 | AS92: 100 | AT92: 100 | AU92: 11
A93: ʧ | B93: 5 | C93: 7 | D93: 7 | E93: 6 | F93: 5 | G93: 4 | H93: 3 | I93: 2 | J93: 3 | K93: 1 | L93: 0 | M93: 4 | N93: 3 | O93: 2 | P93: 1 | Q93: 2 | R93: 3 | S93: 3 | T93: 4 | U93: 6 | V93: 9 | W93: 10 | X93: 9 | Y93: 9 | Z93: 100 | AA93: 100 | AB93: 100 | AC93: 100 | AD93: 100 | AE93: 100 | AF93: 100 | AG93: 100 | AH93: 100 | AI93: 100 | AJ93: 100 | AK93: 100 | AL93: 100 | AM93: 100 | AN93: 100 | AO93: 100 | AP93: 100 | AQ93: 100 | AR93: 100 | AS93: 100 | AT93: 100 | AU93: 12
A94: d | B94: 4 | C94: 6 | D94: 7 | E94: 10 | F94: 7 | G94: 6 | H94: 5 | I94: 4 | J94: 1 | K94: 3 | L94: 4 | M94: 0 | N94: 1 | O94: 2 | P94: 3 | Q94: 4 | R94: 5 | S94: 3 | T94: 4 | U94: 7 | V94: 5 | W94: 6 | X94: 7 | Y94: 9 | Z94: 100 | AA94: 100 | AB94: 100 | AC94: 100 | AD94: 100 | AE94: 100 | AF94: 100 | AG94: 100 | AH94: 100 | AI94: 100 | AJ94: 100 | AK94: 100 | AL94: 100 | AM94: 100 | AN94: 100 | AO94: 100 | AP94: 100 | AQ94: 100 | AR94: 100 | AS94: 100 | AT94: 100 | AU94: 13
... A127: jʊə | B127: 100 | C127: 100 | D127: 100 | E127: 100 | F127: 100 | G127: 100 | H127: 100 | I127: 100 | J127: 100 | K127: 100 | L127: 100 | M127: 100 | N127: 100 | O127: 100 | P127: 100 | Q127: 100 | R127: 100 | S127: 100 | T127: 100 | U127: 100 | V127: 100 | W127: 100 | X127: 100 | Y127: 100 | Z127: 9 | AA127: 8 | AB127: 7 | AC127: 6 | AD127: 5 | AE127: 4 | AF127: 8 | AG127: 7 | AH127: 6 | AI127: 5 | AJ127: 4 | AK127: 7 | AL127: 6 | AM127: 5 | AN127: 6 | AO127: 5 | AP127: 4 | AQ127: 3 | AR127: 2 | AS127: 1 | AT127: 0 | AU127: 46
A146: conversion chart 2 | B146: p | C146: b | D146: m | E146: w | F146: f | G146: v | H146: θ | I146: ð | J146: t | K146: s | L146: ʧ | M146: d | N146: n | O146: z | P146: ʤ | Q146: r | R146: l | S146: ʃ | T146: ʒ | U146: jə | V146: k | W146: g | X146: ŋ | Y146: h | Z146: æ | AA146: ɛ | AB146: ɪ | AC146: ɒ | AD146: ʌ | AE146: ʊ | AF146: eɪ | AG146: i | AH146: aɪ | AI146: əʊ | AJ146: u | AK146: ɑ | AL146: ɜ | AM146: ɔ | AN146: ju | AO146: ɔɪ | AP146: aʊ | AQ146: ə | AR146: e | AS146: ɪə | AT146: jʊə
A147: p | B147: =ROUND(POWER(3/4,B83),2) -> 1 | C147: =ROUND(POWER(3/4,C83),2) -> 0.75 | D147: =ROUND(POWER(3/4,D83),2) -> 0.56 | E147: =ROUND(POWER(3/4,E83),2) -> 0.24 | F147: =ROUND(POWER(3/4,F83),2) -> 0.32 | G147: =ROUND(POWER(3/4,G83),2) -> 0.24 | H147: =ROUND(POWER(3/4,H83),2) -> 0.18 | I147: =ROUND(POWER(3/4,I83),2) -> 0.13 | ... AT147: =ROUND(POWER(3/4,AT83),2) -> 0
A148: b | B148: =ROUND(POWER(3/4,B84),2) -> 0.75 | C148: =ROUND(POWER(3/4,C84),2) -> 1 | D148: =ROUND(POWER(3/4,D84),2) -> 0.75 | E148: =ROUND(POWER(3/4,E84),2) -> 0.32 | F148: =ROUND(POWER(3/4,F84),2) -> 0.42 | G148: =ROUND(POWER(3/4,G84),2) -> 0.32 | H148: =ROUND(POWER(3/4,H84),2) -> 0.24 | I148: =ROUND(POWER(3/4,I84),2) -> 0.18 | ... AT148: =ROUND(POWER(3/4,AT84),2) -> 0
A149: m | B149: =ROUND(POWER(3/4,B85),2) -> 0.56 | C149: =ROUND(POWER(3/4,C85),2) -> 0.75 | D149: =ROUND(POWER(3/4,D85),2) -> 1 | E149: =ROUND(POWER(3/4,E85),2) -> 0.42 | F149: =ROUND(POWER(3/4,F85),2) -> 0.56 | G149: =ROUND(POWER(3/4,G85),2) -> 0.42 | H149: =ROUND(POWER(3/4,H85),2) -> 0.32 | I149: =ROUND(POWER(3/4,I85),2) -> 0.24 | ... AT149: =ROUND(POWER(3/4,AT85),2) -> 0
A150: w | B150: =ROUND(POWER(3/4,B86),2) -> 0.24 | C150: =ROUND(POWER(3/4,C86),2) -> 0.32 | D150: =ROUND(POWER(3/4,D86),2) -> 0.42 | E150: =ROUND(POWER(3/4,E86),2) -> 1 | F150: =ROUND(POWER(3/4,F86),2) -> 0.42 | G150: =ROUND(POWER(3/4,G86),2) -> 0.32 | H150: =ROUND(POWER(3/4,H86),2) -> 0.24 | I150: =ROUND(POWER(3/4,I86),2) -> 0.18 | ... AT150: =ROUND(POWER(3/4,AT86),2) -> 0
A151: f | B151: =ROUND(POWER(3/4,B87),2) -> 0.32 | C151: =ROUND(POWER(3/4,C87),2) -> 0.42 | D151: =ROUND(POWER(3/4,D87),2) -> 0.56 | E151: =ROUND(POWER(3/4,E87),2) -> 0.42 | F151: =ROUND(POWER(3/4,F87),2) -> 1 | G151: =ROUND(POWER(3/4,G87),2) -> 0.75 | H151: =ROUND(POWER(3/4,H87),2) -> 0.56 | I151: =ROUND(POWER(3/4,I87),2) -> 0.42 | ... AT151: =ROUND(POWER(3/4,AT87),2) -> 0
A152: v | B152: =ROUND(POWER(3/4,B88),2) -> 0.24 | C152: =ROUND(POWER(3/4,C88),2) -> 0.32 | D152: =ROUND(POWER(3/4,D88),2) -> 0.42 | E152: =ROUND(POWER(3/4,E88),2) -> 0.56 | F152: =ROUND(POWER(3/4,F88),2) -> 0.75 | G152: =ROUND(POWER(3/4,G88),2) -> 1 | H152: =ROUND(POWER(3/4,H88),2) -> 0.75 | I152: =ROUND(POWER(3/4,I88),2) -> 0.56 | ... AT152: =ROUND(POWER(3/4,AT88),2) -> 0
A153: θ | B153: =ROUND(POWER(3/4,B89),2) -> 0.24 | C153: =ROUND(POWER(3/4,C89),2) -> 0.24 | D153: =ROUND(POWER(3/4,D89),2) -> 0.32 | E153: =ROUND(POWER(3/4,E89),2) -> 0.24 | F153: =ROUND(POWER(3/4,F89),2) -> 0.56 | G153: =ROUND(POWER(3/4,G89),2) -> 0.75 | H153: =ROUND(POWER(3/4,H89),2) -> 1 | I153: =ROUND(POWER(3/4,I89),2) -> 0.75 | ... AT153: =ROUND(POWER(3/4,AT89),2) -> 0
A154: ð | B154: =ROUND(POWER(3/4,B90),2) -> 0.32 | C154: =ROUND(POWER(3/4,C90),2) -> 0.18 | D154: =ROUND(POWER(3/4,D90),2) -> 0.24 | E154: =ROUND(POWER(3/4,E90),2) -> 0.18 | F154: =ROUND(POWER(3/4,F90),2) -> 0.42 | G154: =ROUND(POWER(3/4,G90),2) -> 0.56 | H154: =ROUND(POWER(3/4,H90),2) -> 0.75 | I154: =ROUND(POWER(3/4,I90),2) -> 1 | ... AT154: =ROUND(POWER(3/4,AT90),2) -> 0
A155: t | B155: =ROUND(POWER(3/4,B91),2) -> 0.24 | C155: =ROUND(POWER(3/4,C91),2) -> 0.24 | D155: =ROUND(POWER(3/4,D91),2) -> 0.18 | E155: =ROUND(POWER(3/4,E91),2) -> 0.08 | F155: =ROUND(POWER(3/4,F91),2) -> 0.18 | G155: =ROUND(POWER(3/4,G91),2) -> 0.24 | H155: =ROUND(POWER(3/4,H91),2) -> 0.32 | I155: =ROUND(POWER(3/4,I91),2) -> 0.42 | ... AT155: =ROUND(POWER(3/4,AT91),2) -> 0
A156: s | B156: =ROUND(POWER(3/4,B92),2) -> 0.32 | C156: =ROUND(POWER(3/4,C92),2) -> 0.18 | D156: =ROUND(POWER(3/4,D92),2) -> 0.18 | E156: =ROUND(POWER(3/4,E92),2) -> 0.13 | F156: =ROUND(POWER(3/4,F92),2) -> 0.32 | G156: =ROUND(POWER(3/4,G92),2) -> 0.42 | H156: =ROUND(POWER(3/4,H92),2) -> 0.56 | I156: =ROUND(POWER(3/4,I92),2) -> 0.75 | ... AT156: =ROUND(POWER(3/4,AT92),2) -> 0
A157: ʧ | B157: =ROUND(POWER(3/4,B93),2) -> 0.24 | C157: =ROUND(POWER(3/4,C93),2) -> 0.13 | D157: =ROUND(POWER(3/4,D93),2) -> 0.13 | E157: =ROUND(POWER(3/4,E93),2) -> 0.18 | F157: =ROUND(POWER(3/4,F93),2) -> 0.24 | G157: =ROUND(POWER(3/4,G93),2) -> 0.32 | H157: =ROUND(POWER(3/4,H93),2) -> 0.42 | I157: =ROUND(POWER(3/4,I93),2) -> 0.56 | ... AT157: =ROUND(POWER(3/4,AT93),2) -> 0
A158: d | B158: =ROUND(POWER(3/4,B94),2) -> 0.32 | C158: =ROUND(POWER(3/4,C94),2) -> 0.18 | D158: =ROUND(POWER(3/4,D94),2) -> 0.13 | E158: =ROUND(POWER(3/4,E94),2) -> 0.06 | F158: =ROUND(POWER(3/4,F94),2) -> 0.13 | G158: =ROUND(POWER(3/4,G94),2) -> 0.18 | H158: =ROUND(POWER(3/4,H94),2) -> 0.24 | I158: =ROUND(POWER(3/4,I94),2) -> 0.32 | ... AT158: =ROUND(POWER(3/4,AT94),2) -> 0
... A191: jʊə | B191: =ROUND(POWER(3/4,B127),2) -> 0 | C191: =ROUND(POWER(3/4,C127),2) -> 0 | D191: =ROUND(POWER(3/4,D127),2) -> 0 | E191: =ROUND(POWER(3/4,E127),2) -> 0 | F191: =ROUND(POWER(3/4,F127),2) -> 0 | G191: =ROUND(POWER(3/4,G127),2) -> 0 | H191: =ROUND(POWER(3/4,H127),2) -> 0 | I191: =ROUND(POWER(3/4,I127),2) -> 0 | ... AT191: =ROUND(POWER(3/4,AT127),2) -> 1
A201: Random | B201: p | C201: b | D201: m | E201: w | F201: f | G201: v | H201: θ | I201: ð | J201: t | K201: s | L201: ʧ | M201: d | N201: n | O201: z | P201: ʤ | Q201: r | R201: l | S201: ʃ | T201: ʒ | U201: jə | V201: k | W201: g | X201: ŋ | Y201: h | Z201: " | AA201: æ | AB201: ɛ | AC201: ɪ | AD201: ɒ | AE201: ʌ | AF201: ʊ | AG201: eɪ | AH201: i | AI201: aɪ | AJ201: əʊ | AK201: u | AL201: ɑ | AM201: ɜ | AN201: ɔ | AO201: ju | AP201: ɔɪ | AQ201: aʊ | AR201: ə | AS201: e | AT201: ɪə | AU201: jʊə
B202: =RAND() -> 0.7540757 | C202: =RAND() -> 0.89610278 | D202: =RAND() -> 0.84869994 | E202: =RAND() -> 0.36023869 | F202: =RAND() -> 0.28232997 | G202: =RAND() -> 0.71733137 | H202: =RAND() -> 0.36170857 | I202: =RAND() -> 0.91684958 | ... AU202: =RAND() -> 0.12986764
A204: Speech number | B204: p | C204: b | D204: m | E204: w | F204: f | G204: v | H204: θ | I204: ð | J204: t | K204: s | L204: ʧ | M204: d | N204: n | O204: z | P204: ʤ | Q204: r | R204: l | S204: ʃ | T204: ʒ | U204: jə | V204: k | W204: g | X204: ŋ | Y204: h | Z204: " | AA204: æ | AB204: ɛ | AC204: ɪ | AD204: ɒ | AE204: ʌ | AF204: ʊ | AG204: eɪ | AH204: i | AI204: aɪ | AJ204: əʊ | AK204: u | AL204: ɑ | AM204: ɜ | AN204: ɔ | AO204: ju | AP204: ɔɪ | AQ204: aʊ | AR204: ə | AS204: e | AT204: ɪə | AU204: jʊə
B205: =B71 -> 0.010416667 | C205: =C71 -> 0.020833333 | D205: =C72 -> 0.041666667 | E205: =C75 -> 0.10416667 | F205: =D73 -> 0.09375 | G205: =E73 -> 0.125 | H205: =F73 -> 0.15625 | I205: =G73 -> 0.1875 | J205: =H71 -> 0.072916667 | K205: =I73 -> 0.25 | L205: =H74 -> 0.29166667 | M205: =I71 -> 0.083333333 | N205: =I72 -> 0.16666667 | O205: =I73 -> 0.25 | P205: =I74 -> 0.33333333 | Q205: =I75 -> 0.41666667 | R205: =I76 -> 0.5 | S205: =J73 -> 0.28125 | T205: =K73 -> 0.3125 | U205: =M75 -> 0.625 | V205: =N71 -> 0.13541667 | W205: =O71 -> 0.14583333 | X205: =O72 -> 0.29166667 | Y205: =P73 -> 0.46875 | Z205: =Z202 -> 0.3631622 | AA205: =V70 -> 0.035714286 | AB205: =W70 -> 0.071428571 | AC205: =X70 -> 0.10714286 | AD205: =Y70 -> 0.14285714 | AE205: =Z70 -> 0.17857143 | AF205: =AA70 -> 0.21428571 | AG205: =V71 -> 0.071428571 | AH205: =W71 -> 0.14285714 | AI205: =X71 -> 0.21428571 | AJ205: =Y71 -> 0.28571429 | AK205: =AA71 -> 0.42857143 | AL205: =V72 -> 0.10714286 | AM205: =W72 -> 0.21428571 | AN205: =X72 -> 0.32142857 | AO205: =V73 -> 0.14285714 | AP205: =W73 -> 0.28571429 | AQ205: =X73 -> 0.42857143 | AR205: =Y73 -> 0.57142857 | AS205: =Z73 -> 0.71428571 | AT205: =AA73 -> 0.85714286 | AU205: =AB73 -> 1
A212: conversion chart 3 | B212: p | C212: b | D212: m | E212: w | F212: f | G212: v | H212: θ | I212: ð | J212: t | K212: s | L212: ʧ | M212: d | N212: n | O212: z | P212: ʤ | Q212: r | R212: l | S212: ʃ | T212: ʒ | U212: jə | V212: k | W212: g | X212: ŋ | Y212: h | Z212: " | AA212: æ | AB212: ɛ | AC212: ɪ | AD212: ɒ | AE212: ʌ | AF212: ʊ | AG212: eɪ | AH212: i | AI212: aɪ | AJ212: əʊ | AK212: u | AL212: ɑ | AM212: ɜ | AN212: ɔ | AO212: ju | AP212: ɔɪ | AQ212: aʊ | AR212: ə | AS212: e | AT212: ɪə | AU212: jʊə
A213: p | B213: =B147*B$202*B$205 -> 0.0078549552 | C213: =C147*C$202*C$205 -> 0.014001606 | D213: =D147*D$202*D$205 -> 0.019802999 | E213: =E147*E$202*E$205 -> 0.0090059673 | F213: =F147*F$202*F$205 -> 0.008469899 | G213: =G147*G$202*G$205 -> 0.021519941 | H213: =H147*H$202*H$205 -> 0.010173054 | I213: =I147*I$202*I$205 -> 0.022348209 | ... Y213: =Y147*Y$202*Y$205 -> 0.001781512 | Z213: =$Z$205 -> 0.3631622 | AA213: =Z147*AA$202*AA$205 -> 0 | AB213: =AA147*AB$202*AB$205 -> 0 | AC213: =AB147*AC$202*AC$205 -> 0 | AD213: =AC147*AD$202*AD$205 -> 0 | AE213: =AD147*AE$202*AE$205 -> 0 | AF213: =AE147*AF$202*AF$205 -> 0 | AG213: =AF147*AG$202*AG$205 -> 0 | AH213: =AG147*AH$202*AH$205 -> 0 | ... AU213: =AT147*AU$202*AU$205 -> 0 | AV213: =SUM(B213:AU213) -> 0.59904805
A214: b | B214: =B148*B$202*B$205 -> 0.0058912164 | C214: =C148*C$202*C$205 -> 0.018668808 | D214: =D148*D$202*D$205 -> 0.026521873 | E214: =E148*E$202*E$205 -> 0.012007956 | F214: =F148*F$202*F$205 -> 0.011116742 | G214: =G148*G$202*G$205 -> 0.028693255 | H214: =H148*H$202*H$205 -> 0.013564071 | I214: =I148*I$202*I$205 -> 0.030943673 | ... Y214: =Y148*Y$202*Y$205 -> 0.001781512 | Z214: =$Z$205 -> 0.3631622 | AA214: =Z148*AA$202*AA$205 -> 0 | AB214: =AA148*AB$202*AB$205 -> 0 | AC214: =AB148*AC$202*AC$205 -> 0 | AD214: =AC148*AD$202*AD$205 -> 0 | AE214: =AD148*AE$202*AE$205 -> 0 | AF214: =AE148*AF$202*AF$205 -> 0 | AG214: =AF148*AG$202*AG$205 -> 0 | AH214: =AG148*AH$202*AH$205 -> 0 | ... AU214: =AT148*AU$202*AU$205 -> 0 | AV214: =SUM(B214:AU214) -> 0.67368176
A215: m | B215: =B149*B$202*B$205 -> 0.0043987749 | C215: =C149*C$202*C$205 -> 0.014001606 | D215: =D149*D$202*D$205 -> 0.035362498 | E215: =E149*E$202*E$205 -> 0.015760443 | F215: =F149*F$202*F$205 -> 0.014822323 | G215: =G149*G$202*G$205 -> 0.037659897 | H215: =H149*H$202*H$205 -> 0.018085429 | I215: =I149*I$202*I$205 -> 0.041258231 | ... Y215: =Y149*Y$202*Y$205 -> 0.0035630241 | Z215: =$Z$205 -> 0.3631622 | AA215: =Z149*AA$202*AA$205 -> 0 | AB215: =AA149*AB$202*AB$205 -> 0 | AC215: =AB149*AC$202*AC$205 -> 0 | AD215: =AC149*AD$202*AD$205 -> 0 | AE215: =AD149*AE$202*AE$205 -> 0 | AF215: =AE149*AF$202*AF$205 -> 0 | AG215: =AF149*AG$202*AG$205 -> 0 | AH215: =AG149*AH$202*AH$205 -> 0 | ... AU215: =AT149*AU$202*AU$205 -> 0 | AV215: =SUM(B215:AU215) -> 0.73031879
A216: w | B216: =B150*B$202*B$205 -> 0.0018851893 | C216: =C150*C$202*C$205 -> 0.0059740185 | D216: =D150*D$202*D$205 -> 0.014852249 | E216: =E150*E$202*E$205 -> 0.037524864 | F216: =F150*F$202*F$205 -> 0.011116742 | G216: =G150*G$202*G$205 -> 0.028693255 | H216: =H150*H$202*H$205 -> 0.013564071 | I216: =I150*I$202*I$205 -> 0.030943673 | ... Y216: =Y150*Y$202*Y$205 -> 0.001781512 | Z216: =$Z$205 -> 0.3631622 | AA216: =Z150*AA$202*AA$205 -> 0 | AB216: =AA150*AB$202*AB$205 -> 0 | AC216: =AB150*AC$202*AC$205 -> 0 | AD216: =AC150*AD$202*AD$205 -> 0 | AE216: =AD150*AE$202*AE$205 -> 0 | AF216: =AE150*AF$202*AF$205 -> 0 | AG216: =AF150*AG$202*AG$205 -> 0 | AH216: =AG150*AH$202*AH$205 -> 0 | ... AU216: =AT150*AU$202*AU$205 -> 0 | AV216: =SUM(B216:AU216) -> 0.71378624
A217: f | B217: =B151*B$202*B$205 -> 0.0025135857 | C217: =C151*C$202*C$205 -> 0.0078408993 | D217: =D151*D$202*D$205 -> 0.019802999 | E217: =E151*E$202*E$205 -> 0.015760443 | F217: =F151*F$202*F$205 -> 0.026468434 | G217: =G151*G$202*G$205 -> 0.067249816 | H217: =H151*H$202*H$205 -> 0.0316495 | I217: =I151*I$202*I$205 -> 0.072201905 | ... Y217: =Y151*Y$202*Y$205 -> 0.0053445361 | Z217: =$Z$205 -> 0.3631622 | AA217: =Z151*AA$202*AA$205 -> 0 | AB217: =AA151*AB$202*AB$205 -> 0 | AC217: =AB151*AC$202*AC$205 -> 0 | AD217: =AC151*AD$202*AD$205 -> 0 | AE217: =AD151*AE$202*AE$205 -> 0 | AF217: =AE151*AF$202*AF$205 -> 0 | AG217: =AF151*AG$202*AG$205 -> 0 | AH217: =AG151*AH$202*AH$205 -> 0 | ... AU217: =AT151*AU$202*AU$205 -> 0 | AV217: =SUM(B217:AU217) -> 0.92039776
A218: v | B218: =B152*B$202*B$205 -> 0.0018851893 | C218: =C152*C$202*C$205 -> 0.0059740185 | D218: =D152*D$202*D$205 -> 0.014852249 | E218: =E152*E$202*E$205 -> 0.021013924 | F218: =F152*F$202*F$205 -> 0.019851326 | G218: =G152*G$202*G$205 -> 0.089666422 | H218: =H152*H$202*H$205 -> 0.042387723 | I218: =I152*I$202*I$205 -> 0.096269206 | ... Y218: =Y152*Y$202*Y$205 -> 0.0071260482 | Z218: =$Z$205 -> 0.3631622 | AA218: =Z152*AA$202*AA$205 -> 0 | AB218: =AA152*AB$202*AB$205 -> 0 | AC218: =AB152*AC$202*AC$205 -> 0 | AD218: =AC152*AD$202*AD$205 -> 0 | AE218: =AD152*AE$202*AE$205 -> 0 | AF218: =AE152*AF$202*AF$205 -> 0 | AG218: =AF152*AG$202*AG$205 -> 0 | AH218: =AG152*AH$202*AH$205 -> 0 | ... AU218: =AT152*AU$202*AU$205 -> 0 | AV218: =SUM(B218:AU218) -> 1.0763376
A219: θ | B219: =B153*B$202*B$205 -> 0.0018851893 | C219: =C153*C$202*C$205 -> 0.0044805139 | D219: =D153*D$202*D$205 -> 0.011315999 | E219: =E153*E$202*E$205 -> 0.0090059673 | F219: =F153*F$202*F$205 -> 0.014822323 | G219: =G153*G$202*G$205 -> 0.067249816 | H219: =H153*H$202*H$205 -> 0.056516964 | I219: =I153*I$202*I$205 -> 0.12893197 | ... Y219: =Y153*Y$202*Y$205 -> 0.010689072 | Z219: =$Z$205 -> 0.3631622 | AA219: =Z153*AA$202*AA$205 -> 0 | AB219: =AA153*AB$202*AB$205 -> 0 | AC219: =AB153*AC$202*AC$205 -> 0 | AD219: =AC153*AD$202*AD$205 -> 0 | AE219: =AD153*AE$202*AE$205 -> 0 | AF219: =AE153*AF$202*AF$205 -> 0 | AG219: =AF153*AG$202*AG$205 -> 0 | AH219: =AG153*AH$202*AH$205 -> 0 | ... AU219: =AT153*AU$202*AU$205 -> 0 | AV219: =SUM(B219:AU219) -> 1.2195779
A220: ð | B220: =B154*B$202*B$205 -> 0.0025135857 | C220: =C154*C$202*C$205 -> 0.0033603854 | D220: =D154*D$202*D$205 -> 0.0084869994 | E220: =E154*E$202*E$205 -> 0.0067544755 | F220: =F154*F$202*F$205 -> 0.011116742 | G220: =G154*G$202*G$205 -> 0.050213196 | H220: =H154*H$202*H$205 -> 0.042387723 | I220: =I154*I$202*I$205 -> 0.1719093 | ... Y220: =Y154*Y$202*Y$205 -> 0.014252096 | Z220: =$Z$205 -> 0.3631622 | AA220: =Z154*AA$202*AA$205 -> 0 | AB220: =AA154*AB$202*AB$205 -> 0 | AC220: =AB154*AC$202*AC$205 -> 0 | AD220: =AC154*AD$202*AD$205 -> 0 | AE220: =AD154*AE$202*AE$205 -> 0 | AF220: =AE154*AF$202*AF$205 -> 0 | AG220: =AF154*AG$202*AG$205 -> 0 | AH220: =AG154*AH$202*AH$205 -> 0 | ... AU220: =AT154*AU$202*AU$205 -> 0 | AV220: =SUM(B220:AU220) -> 1.4034408
A221: t | B221: =B155*B$202*B$205 -> 0.0018851893 | C221: =C155*C$202*C$205 -> 0.0044805139 | D221: =D155*D$202*D$205 -> 0.0063652496 | E221: =E155*E$202*E$205 -> 0.0030019891 | F221: =F155*F$202*F$205 -> 0.0047643182 | G221: =G155*G$202*G$205 -> 0.021519941 | H221: =H155*H$202*H$205 -> 0.018085429 | I221: =I155*I$202*I$205 -> 0.072201905 | ... Y221: =Y155*Y$202*Y$205 -> 0.010689072 | Z221: =$Z$205 -> 0.3631622 | AA221: =Z155*AA$202*AA$205 -> 0 | AB221: =AA155*AB$202*AB$205 -> 0 | AC221: =AB155*AC$202*AC$205 -> 0 | AD221: =AC155*AD$202*AD$205 -> 0 | AE221: =AD155*AE$202*AE$205 -> 0 | AF221: =AE155*AF$202*AF$205 -> 0 | AG221: =AF155*AG$202*AG$205 -> 0 | AH221: =AG155*AH$202*AH$205 -> 0 | ... AU221: =AT155*AU$202*AU$205 -> 0 | AV221: =SUM(B221:AU221) -> 1.1361409
A222: s | B222: =B156*B$202*B$205 -> 0.0025135857 | C222: =C156*C$202*C$205 -> 0.0033603854 | D222: =D156*D$202*D$205 -> 0.0063652496 | E222: =E156*E$202*E$205 -> 0.0048782323 | F222: =F156*F$202*F$205 -> 0.008469899 | G222: =G156*G$202*G$205 -> 0.037659897 | H222: =H156*H$202*H$205 -> 0.0316495 | I222: =I156*I$202*I$205 -> 0.12893197 | ... Y222: =Y156*Y$202*Y$205 -> 0.01781512 | Z222: =$Z$205 -> 0.3631622 | AA222: =Z156*AA$202*AA$205 -> 0 | AB222: =AA156*AB$202*AB$205 -> 0 | AC222: =AB156*AC$202*AC$205 -> 0 | AD222: =AC156*AD$202*AD$205 -> 0 | AE222: =AD156*AE$202*AE$205 -> 0 | AF222: =AE156*AF$202*AF$205 -> 0 | AG222: =AF156*AG$202*AG$205 -> 0 | AH222: =AG156*AH$202*AH$205 -> 0 | ... AU222: =AT156*AU$202*AU$205 -> 0 | AV222: =SUM(B222:AU222) -> 1.5746458
A223: ʧ | B223: =B157*B$202*B$205 -> 0.0018851893 | C223: =C157*C$202*C$205 -> 0.002426945 | D223: =D157*D$202*D$205 -> 0.0045971247 | E223: =E157*E$202*E$205 -> 0.0067544755 | F223: =F157*F$202*F$205 -> 0.0063524242 | G223: =G157*G$202*G$205 -> 0.028693255 | H223: =H157*H$202*H$205 -> 0.023737125 | I223: =I157*I$202*I$205 -> 0.096269206 | ... Y223: =Y157*Y$202*Y$205 -> 0.014252096 | Z223: =$Z$205 -> 0.3631622 | AA223: =Z157*AA$202*AA$205 -> 0 | AB223: =AA157*AB$202*AB$205 -> 0 | AC223: =AB157*AC$202*AC$205 -> 0 | AD223: =AC157*AD$202*AD$205 -> 0 | AE223: =AD157*AE$202*AE$205 -> 0 | AF223: =AE157*AF$202*AF$205 -> 0 | AG223: =AF157*AG$202*AG$205 -> 0 | AH223: =AG157*AH$202*AH$205 -> 0 | ... AU223: =AT157*AU$202*AU$205 -> 0 | AV223: =SUM(B223:AU223) -> 1.5719675
A224: d | B224: =B158*B$202*B$205 -> 0.0025135857 | C224: =C158*C$202*C$205 -> 0.0033603854 | D224: =D158*D$202*D$205 -> 0.0045971247 | E224: =E158*E$202*E$205 -> 0.0022514918 | F224: =F158*F$202*F$205 -> 0.0034408965 | G224: =G158*G$202*G$205 -> 0.016139956 | H224: =H158*H$202*H$205 -> 0.013564071 | I224: =I158*I$202*I$205 -> 0.055010975 | ... Y224: =Y158*Y$202*Y$205 -> 0.014252096 | Z224: =$Z$205 -> 0.3631622 | AA224: =Z158*AA$202*AA$205 -> 0 | AB224: =AA158*AB$202*AB$205 -> 0 | AC224: =AB158*AC$202*AC$205 -> 0 | AD224: =AC158*AD$202*AD$205 -> 0 | AE224: =AD158*AE$202*AE$205 -> 0 | AF224: =AE158*AF$202*AF$205 -> 0 | AG224: =AF158*AG$202*AG$205 -> 0 | AH224: =AG158*AH$202*AH$205 -> 0 | ... AU224: =AT158*AU$202*AU$205 -> 0 | AV224: =SUM(B224:AU224) -> 1.2155768
... A257: jʊə | B257: =B191*B$202*B$205 -> 0 | C257: =C191*C$202*C$205 -> 0 | D257: =D191*D$202*D$205 -> 0 | E257: =E191*E$202*E$205 -> 0 | F257: =F191*F$202*F$205 -> 0 | G257: =G191*G$202*G$205 -> 0 | H257: =H191*H$202*H$205 -> 0 | I257: =I191*I$202*I$205 -> 0 | ... Y257: =Y191*Y$202*Y$205 -> 0 | Z257: =$Z$205 -> 0.3631622 | AA257: =Z191*AA$202*AA$205 -> 0.00032983251 | AB257: =AA191*AB$202*AB$205 -> 0.0033727374 | AC257: =AB191*AC$202*AC$205 -> 0.0015463219 | AD257: =AC191*AD$202*AD$205 -> 0.015353755 | AE257: =AD191*AE$202*AE$205 -> 0.003331086 | AF257: =AE191*AF$202*AF$205 -> 0.04269728 | AG257: =AF191*AG$202*AG$205 -> 0.0061745371 | AH257: =AG191*AH$202*AH$205 -> 0.015193275 | ... AU257: =AT191*AU$202*AU$205 -> 0.12986764 | AV257: =SUM(B257:AU257) -> 1.3144598
A262: conversion chart 4 | B262: p | C262: b | D262: m | E262: w | F262: f | G262: v | H262: θ | I262: ð | J262: t | K262: s | L262: ʧ | M262: d | N262: n | O262: z | P262: ʤ | Q262: r | R262: l | S262: ʃ | T262: ʒ | U262: jə | V262: k | W262: g | X262: ŋ | Y262: h | Z262: " | AA262: æ | AB262: ɛ | AC262: ɪ | AD262: ɒ | AE262: ʌ | AF262: ʊ | AG262: eɪ | AH262: i | AI262: aɪ | AJ262: əʊ | AK262: u | AL262: ɑ | AM262: ɜ | AN262: ɔ | AO262: ju | AP262: ɔɪ | AQ262: aʊ | AR262: ə | AS262: e | AT262: ɪə | AU262: jʊə
A263: p | B263: =B213/$AV213 -> 0.013112396 | C263: =C213/$AV213 -> 0.023373093 | D263: =D213/$AV213 -> 0.033057446 | E263: =E213/$AV213 -> 0.015033798 | F263: =F213/$AV213 -> 0.014138931 | G263: =G213/$AV213 -> 0.035923564 | H263: =H213/$AV213 -> 0.016982033 | I263: =I213/$AV213 -> 0.037306203 | ... AU263: =AU213/$AV213 -> 0
A264: b | B264: =B214/$AV214 -> 0.0087448061 | C264: =C214/$AV214 -> 0.027711612 | D264: =D214/$AV214 -> 0.039368549 | E264: =E214/$AV214 -> 0.017824375 | F264: =F214/$AV214 -> 0.016501474 | G264: =G214/$AV214 -> 0.042591705 | H264: =H214/$AV214 -> 0.020134242 | I264: =I214/$AV214 -> 0.045932182 | ... AU264: =AU214/$AV214 -> 0
...

Sheet All Words All Languages
A1: Word | B1: Pronunciation | C1: New Words Vocal | D1: New Words Spelling | E1: Type | H1: Pronunciation | I1: 1 | J1: New Words Vocal | K1: New Words Spelling | N1: New Words Spelling
A2: a | B2: eɪ/ | C2: "///////////// | D2: " | E2: OPERATIONS | F2: 1 | H2: =B2 -> eɪ/ | L2: 1 | N2: oy
A3: able | B3: eɪ/b/ə/l/ | C3: "/"/ɜ/r////////// | D3: ""ourwr | E3: QUALITIES | F3: 2 | H3: =B3 -> eɪ/b/ə/l/ | N3: ier"ir"
A4: about | B4: ə/b/aʊ/t/ | C4: ɪə/"/"/"////////// | D4: ier""" | E4: OPERATIONS | F4: 3 | H4: =B4 -> ə/b/aʊ/t/ | L4: =L2+1 -> 2 | N4: ""owdd
A5: account | B5: ə/k/aʊ/n/t/ | C5: "/r/"/d/"///////// | D5: "wr"dd" | E5: THINGS | F5: 4 | H5: =B5 -> ə/k/aʊ/n/t/ | N5: ""ou"ze
A6: acid | B6: æ/s/ə/d/ | C6: "/"/ɪə/jə////////// | D6: ""eeri | E6: QUALITIES | F6: 5 | H6: =B6 -> æ/s/ə/d/ | L6: =L4+1 -> 3 | N6: a"u"
A7: across | B7: ə/k/r/ɔ/s/ | C7: "/z/z/ɔ/"///////// | D7: "zzzzaw" | E7: OPERATIONS | F7: 6 | H7: =B7 -> ə/k/r/ɔ/s/ | N7: """owti
A8: act | B8: æ/k/t/ | C8: "/"/r/////////// | D8: ""rh | E8: THINGS | F8: 7 | H8: =B8 -> æ/k/t/ | L8: =L6+1 -> 4 | N8: "gh"
A9: addition | B9: ə/d/ɪ/ʃ/ə/n/ | C9: e/ʤ/ə/ʃ/u/"//////// | D9: eardiisoeu" | E9: THINGS | F9: 8 | H9: =B9 -> ə/d/ɪ/ʃ/ə/n/ | N9: "z"rh"f
A10: adjustment | B10: ə/ʤ/ʌ/s/t/m/ə/n/t/ | C10: "/ʤ/"/"/"/"/"/"/"///// | D10: "dge""""""" | E10: THINGS | F10: 9 | H10: =B10 -> ə/ʤ/ʌ/s/t/m/ə/n/t/ | L10: =L8+1 -> 5 | N10: ossopn"n"tic
A11: advertisement | B11: ə/d/v/ɜ/r/t/ə/z/m/ə/n/t/ | C11: ɪə/ʤ/m/aɪ/ʃ/ʧ/ʌ/"/ʒ/ə/"/"// | D11: eerdimnaishteoo"si"" | E11: THINGS | F11: 10 | H11: =B11 -> ə/d/v/ɜ/r/t/ə/z/m/ə/n/t/ | N11: you"ftoi"""sez""se
A12: after | B12: æ/f/t/ə/r/ | C12: "/"/"/ə/r///////// | D12: """iwr | E12: OPERATIONS | F12: 11 | H12: =B12 -> æ/f/t/ə/r/ | L12: =L10+1 -> 6 | N12: oi""""
A13: again | B13: ə/g/ɛ/n/ | C13: ɪə/"/ɛ/ŋ////////// | D13: ear"ein | E13: OPERATIONS | F13: 12 | H13: =B13 -> ə/g/ɛ/n/ | N13: yu""te
A14: against | B14: ə/g/ɛ/n/s/t/ | C14: u/"/ju/"/r/z//////// | D14: ough"you"rhss | E14: OPERATIONS | F14: 13 | H14: =B14 -> ə/g/ɛ/n/s/t/ | L14: =L12+1 -> 7 | N14: ""ow"""
A15: agreement | B15: ə/g/r/i/m/ə/n/t/ | C15: "/ŋ/ʤ/ɪə/"/jʊə/"/"////// | D15: "ngdiere"our"" | E15: THINGS | F15: 14 | H15: =B15 -> ə/g/r/i/m/ə/n/t/ | N15: eiz"oux"th"
A16: air | B16: ɛ/r/ | C16: "/r//////////// | D16: "" | E16: THINGS | F16: 15 | H16: =B16 -> ɛ/r/ | L16: =L14+1 -> 8 | N16: eigh"
A17: all | B17: ɔ/l/ | C17: ɪə/ʤ//////////// | D17: erej | E17: OPERATIONS | F17: 16 | H17: =B17 -> ɔ/l/ | N17: ""
A18: almost | B18: ɔ/l/m/o/ʊ/s/t/ | C18: ɪə/ʤ/"//"/θ/ʤ/////// | D18: eredge""thg | E18: OPERATIONS | F18: 17 | H18: =B18 -> ɔ/l/m/o/ʊ/s/t/ | L18: =L16+1 -> 9 | N18: ow""oof"
A19: among | B19: ə/m/ʌ/ŋ/ | C19: e/"/ɛ/"////////// | D19: eir"ae" | E19: OPERATIONS | F19: 18 | H19: =B19 -> ə/m/ʌ/ŋ/ | N19: oi"""
A20: amount | B20: ə/m/aʊ/n/t/ | C20: ɪə/"/jʊə/"/r///////// | D20: ere"our"r | E20: THINGS | F20: 19 | H20: =B20 -> ə/m/aʊ/n/t/ | L20: =L18+1 -> 10 | N20: ""oughssti
A21: amusement | B21: ə/m/ju/z/m/ə/n/t/ | C21: "/"/ju/jə/w/ɪə/"/ʤ////// | D21: ""ieu"oeer"di | E21: THINGS | F21: 20 | H21: =B21 -> ə/m/ju/z/m/ə/n/t/ | N21: ou"youcedge"""
A22: and | B22: æ/n/d/ | C22: "/"/ŋ/////////// | D22: ""n | E22: OPERATIONS | F22: 21 | H22: =B22 -> æ/n/d/ | L22: =L20+1 -> 11 | N22: ""si
A23: angle | B23: æ/ŋ/g/ə/l/ | C23: i/"/ʤ/i/l///////// | D23: ey"diill | E23: THINGS | F23: 22 | H23: =B23 -> æ/ŋ/g/ə/l/ | N23: ""gueeusi
A24: angry | B24: æ/ŋ/g/r/i/ | C24: "/jə/"/"/ɛ///////// | D24: "i""ai | E24: QUALITIES | F24: 23 | H24: =B24 -> æ/ŋ/g/r/i/ | L24: =L22+1 -> 12 | N24: "gn""oy
A25: animal | B25: æ/n/ə/m/ə/l/ | C25: "/"/jʊə/"/ɪə/z//////// | D25: ""ure"ierzz | E25: THINGS | F25: 24 | H25: =B25 -> æ/n/ə/m/ə/l/ | N25: """phydge
A26: answer | B26: æ/n/s/ə/r/ | C26: əʊ/"/jə/"/"///////// | D26: ow"i"" | E26: THINGS | F26: 25 | H26: =B26 -> æ/n/s/ə/r/ | L26: =L24+1 -> 13 | N26: eau""eu"
A27: ant | B27: æ/n/t/ | C27: "/"/r/////////// | D27: ""wr | E27: THINGS | F27: 26 | H27: =B27 -> æ/n/t/ | N27: ""d
A28: any | B28: ɛ/n/i/ | C28: ɪə/h/u/////////// | D28: earhoeu | E28: OPERATIONS | F28: 27 | H28: =B28 -> ɛ/n/i/ | L28: =L26+1 -> 14 | N28: areftei
A29: apparatus | B29: æ/p/ə/r/æ/t/ə/s/ | C29: ɔ/"/ʊ/"/"/f/e/"////// | D29: aw"o""pheir" | E29: THINGS | F29: 28 | H29: =B29 -> æ/p/ə/r/æ/t/ə/s/ | N29: "ftou"isffiess
A30: apple | B30: æ/p/ə/l/ | C30: "/"/"/r////////// | D30: """rr | E30: THINGS | F30: 29 | H30: =B30 -> æ/p/ə/l/ | L30: =L28+1 -> 15 | N30: "bb"rr
A31: approval | B31: ə/p/r/u/v/ə/l/ | C31: jʊə/"/r/e/ʤ/ə/ʤ/////// | D31: ure""eregeerdi | E31: THINGS | F31: 30 | H31: =B31 -> ə/p/r/u/v/ə/l/ | N31: uy"x""u"
A32: arch | B32: ɑ/r/ʧ/ | C32: jʊə/ʤ/ʃ/////////// | D32: uredgech | E32: THINGS | F32: 31 | H32: =B32 -> ɑ/r/ʧ/ | L32: =L30+1 -> 16 | N32: """
A33: argument | B33: ɑ/r/g/jə/m/ə/n/t/ | C33: "/"/h/"/"/jʊə/ʤ/"////// | D33: ""h""uredi" | E33: THINGS | F33: 32 | H33: =B33 -> ɑ/r/g/jə/m/ə/n/t/ | N33: """"x""z
A34: arm | B34: ɑ/r/m/ | C34: i/"/r/////////// | D34: ie"r | E34: THINGS | F34: 33 | H34: =B34 -> ɑ/r/m/ | L34: =L32+1 -> 17 | N34: ""v
A35: army | B35: ɑ/r/m/i/ | C35: ɔ/"/"/ɪə////////// | D35: oor""ere | E35: THINGS | F35: 34 | H35: =B35 -> ɑ/r/m/i/ | N35: "sc"o
A36: art | B36: ɑ/r/t/ | C36: "/r/"/////////// | D36: "rh" | E36: THINGS | F36: 35 | H36: =B36 -> ɑ/r/t/ | L36: =L34+1 -> 18 | N36: ieu""
A37: as | B37: æ/z/ | C37: "/r//////////// | D37: "" | E37: OPERATIONS | F37: 36 | H37: =B37 -> æ/z/ | N37: ""
A38: at | B38: æ/t/ | C38: e/"//////////// | D38: ayer" | E38: OPERATIONS | F38: 37 | H38: =B38 -> æ/t/ | L38: =L36+1 -> 19 | N38: "ss
A39: attack | B39: ə/t/æ/k/ | C39: ɪə/θ/ɪ/"////////// | D39: eerthie" | E39: THINGS | F39: 38 | H39: =B39 -> ə/t/æ/k/ | N39: ""you"
A40: attempt | B40: ə/t/ɛ/m/p/t/ | C40: ɪə/r/"/"/"/t//////// | D40: ierr"""t | E40: THINGS | F40: 39 | H40: =B40 -> ə/t/ɛ/m/p/t/ | L40: =L38+1 -> 20 | N40: ough"hov""
A41: attention | B41: ə/t/ɛ/n/ʃ/ə/n/ | C41: "/"/ʌ/r/s/ɑ/"/////// | D41: ""ourhceear" | E41: THINGS | F41: 40 | H41: =B41 -> ə/t/ɛ/n/ʃ/ə/n/ | N41: oy"ier"s""
A42: attraction | B42: ə/t/r/æ/k/ʃ/ə/n/ | C42: "/"/ʧ/"/"/ʤ/"/n////// | D42: ""te""j"gn | E42: THINGS | F42: 41 | H42: =B42 -> ə/t/r/æ/k/ʃ/ə/n/ | L42: =L40+1 -> 21 | N42: """"""""
A43: authority | B43: ə/θ/ɔ/r/ə/t/i/ | C43: jʊə/"/"/"/ɪə/r/i/////// | D43: our"""eerrre | E43: THINGS | F43: 42 | H43: =B43 -> ə/θ/ɔ/r/ə/t/i/ | N43: "seur"oy""
A44: automatic | B44: ɔ/t/ə/m/æ/t/ɪ/k/ | C44: ə/"/u/"/i/"/ʌ/ŋ////// | D44: i"ue"ee"on | E44: QUALITIES | F44: 43 | H44: =B44 -> ɔ/t/ə/m/æ/t/ɪ/k/ | L44: =L42+1 -> 22 | N44: usi"say"""
A45: awake | B45: ə/w/eɪ/k/ | C45: ɜ/"/"/ʤ////////// | D45: our""ge | E45: QUALITIES | F45: 44 | H45: =B45 -> ə/w/eɪ/k/ | N45: u"o"
A46: baby | B46: b/eɪ/b/i/ | C46: "/"/"/aɪ////////// | D46: """ie | E46: THINGS | F46: 45 | H46: =B46 -> b/eɪ/b/i/ | L46: =L44+1 -> 23 | N46: dgei""
A47: back | B47: b/æ/k/ | C47: "/"/"/////////// | D47: """ | E47: THINGS | F47: 46 | H47: =B47 -> b/æ/k/ | N47: "oi"
A48: bad | B48: b/æ/d/ | C48: θ/i/"/////////// | D48: thi" | E48: QUALITIES | F48: 47 | H48: =B48 -> b/æ/d/ | L48: =L46+1 -> 24 | N48: ""d
A49: bag | B49: b/æ/g/ | C49: "/"/ŋ/////////// | D49: ""ng | E49: THINGS | F49: 48 | H49: =B49 -> b/æ/g/ | N49: """
A50: balance | B50: b/æ/l/ə/n/s/ | C50: "/ɜ/r/jʊə/r/"//////// | D50: "irrhure"" | E50: THINGS | F50: 49 | H50: =B50 -> b/æ/l/ə/n/s/ | L50: =L48+1 -> 25 | N50: "is"""ze
A51: ball | B51: b/ɔ/l/ | C51: jə/e/"/////////// | D51: "air" | E51: THINGS | F51: 50 | H51: =B51 -> b/ɔ/l/ | N51: ""ss
A52: band | B52: b/æ/n/d/ | C52: "/"/ʤ/"////////// | D52: ""ge" | E52: THINGS | F52: 51 | H52: =B52 -> b/æ/n/d/ | L52: =L50+1 -> 26 | N52: ""zz"
A53: base | B53: b/eɪ/s/ | C53: ŋ/ɪ/ʤ/////////// | D53: ngueiej | E53: THINGS | F53: 52 | H53: =B53 -> b/eɪ/s/ | N53: "earph
A54: basin | B54: b/eɪ/s/ə/n/ | C54: ʧ/"/ʤ/ə/ŋ///////// | D54: ti"diorn | E54: THINGS | F54: 53 | H54: =B54 -> b/eɪ/s/ə/n/ | L54: =L52+1 -> 27 | N54: th""""
A55: basket | B55: b/æ/s/k/ə/t/ | C55: w/e/θ/ŋ/"/"//////// | D55: wh"thng"" | E55: THINGS | F55: 54 | H55: =B55 -> b/æ/s/k/ə/t/ | N55: ffeardgethyou"
A56: bath | B56: b/æ/θ/ | C56: "/əʊ/"/////////// | D56: "ew" | E56: THINGS | F56: 55 | H56: =B56 -> b/æ/θ/ | L56: =L54+1 -> 28 | N56: """
A57: be | B57: b/i/ | C57: "/"//////////// | D57: "" | E57: OPERATIONS | F57: 56 | H57: =B57 -> b/i/ | N57: "ou
A58: beautiful | B58: b/ju/t/ə/f/ə/l/ | C58: "/"/n/ɪə/"/e/"/////// | D58: ""knier"eir" | E58: QUALITIES | F58: 57 | H58: =B58 -> b/ju/t/ə/f/ə/l/ | L58: =L56+1 -> 29 | N58: """"se""
A59: because | B59: b/ɪ/k/ɔ/z/ | C59: θ/jʊə/jə/u/"///////// | D59: thourjui" | E59: OPERATIONS | F59: 58 | H59: =B59 -> b/ɪ/k/ɔ/z/ | N59: "ough"ou"
A60: bed | B60: b/ɛ/d/ | C60: "/ʌ/h/////////// | D60: "oh | E60: THINGS | F60: 59 | H60: =B60 -> b/ɛ/d/ | L60: =L58+1 -> 30 | N60: "ew"
A61: bee | B61: b/i/ | C61: "/"//////////// | D61: "" | E61: THINGS | F61: 60 | H61: =B61 -> b/i/ | N61: "ew
A62: before | B62: b/ɪ/f/ɔ/r/ | C62: θ/"/"/ɑ/"///////// | D62: th""er" | E62: OPERATIONS | F62: 61 | H62: =B62 -> b/ɪ/f/ɔ/r/ | L62: =L60+1 -> 31 | N62: """""
A63: behavior | B63: b/ɪ/h/eɪ/v/jə/r/ | C63: w/jʊə/g/ju/ʤ/r/"/////// | D63: ouregueeuejwr" | E63: THINGS | F63: 62 | H63: =B63 -> b/ɪ/h/eɪ/v/jə/r/ | N63: "ogn"ph""
A64: belief | B64: b/ɪ/l/i/f/ | C64: r/jʊə/ʤ/ɜ/"///////// | D64: wrourdgeor" | E64: THINGS | F64: 63 | H64: =B64 -> b/ɪ/l/i/f/ | L64: =L62+1 -> 32 | N64: j"zy"
A65: bell | B65: b/ɛ/l/ | C65: "/ʌ/ʤ/////////// | D65: "ooj | E65: THINGS | F65: 64 | H65: =B65 -> b/ɛ/l/ | N65: "uy"
A66: bent | B66: b/ɛ/n/t/ | C66: "/"/"/"////////// | D66: """" | E66: QUALITIES | F66: 65 | H66: =B66 -> b/ɛ/n/t/ | L66: =L64+1 -> 33 | N66: geo""
A67: berry | B67: b/ɛ/r/i/ | C67: "/ɜ/"/ʌ////////// | D67: "our"o | E67: THINGS | F67: 66 | H67: =B67 -> b/ɛ/r/i/ | N67: ""jieu
A68: between | B68: b/ɪ/t/w/i/n/ | C68: m/aɪ/"/"/ɛ/jə//////// | D68: mai""eij | E68: OPERATIONS | F68: 67 | H68: =B68 -> b/ɪ/t/w/i/n/ | L68: =L66+1 -> 34 | N68: phuy""uy"
A69: bird | B69: b/ɜ/r/d/ | C69: f/ɪə/ʧ/z////////// | D69: gheerch" | E69: THINGS | F69: 68 | H69: =B69 -> b/ɜ/r/d/ | N69: """ci
A70: birth | B70: b/ɜ/r/θ/ | C70: "/"/r/"////////// | D70: ""rh" | E70: THINGS | F70: 69 | H70: =B70 -> b/ɜ/r/θ/ | L70: =L68+1 -> 35 | N70: """sh
A71: bit | B71: b/ɪ/t/ | C71: θ/"/"/////////// | D71: th"" | E71: THINGS | F71: 70 | H71: =B71 -> b/ɪ/t/ | N71: """
A72: bite | B72: b/aɪ/t/ | C72: "/u/"/////////// | D72: "oeu" | E72: THINGS | F72: 71 | H72: =B72 -> b/aɪ/t/ | L72: =L70+1 -> 36 | N72: diow"
A73: bitter | B73: b/ɪ/t/ə/r/ | C73: "/"/r/ɪə/"///////// | D73: ""rrere" | E73: QUALITIES | F73: 72 | H73: =B73 -> b/ɪ/t/ə/r/ | N73: s"f"n
A74: black | B74: b/l/æ/k/ | C74: "/r/"/ŋ////////// | D74: "rr"ng | E74: QUALITIES | F74: 73 | H74: =B74 -> b/l/æ/k/ | L74: =L72+1 -> 37 | N74: ""eigue
A75: blade | B75: b/l/eɪ/d/ | C75: "/"/e/θ////////// | D75: ""ayerth | E75: THINGS | F75: 74 | H75: =B75 -> b/l/eɪ/d/ | N75: "ed""
A76: blood | B76: b/l/ʌ/d/ | C76: "/h/"/"////////// | D76: "h"" | E76: THINGS | F76: 75 | H76: =B76 -> b/l/ʌ/d/ | L76: =L74+1 -> 38 | N76: "ci"ss
A77: blow | B77: b/l/o/ʊ/ | C77: "/r//e////////// | D77: "rrere | E77: THINGS | F77: 76 | H77: =B77 -> b/l/o/ʊ/ | N77: ppll"
A78: blue | B78: b/l/u/ | C78: jə/ʧ/ɪə/////////// | D78: jchear | E78: QUALITIES | F78: 77 | H78: =B78 -> b/l/u/ | L78: =L76+1 -> 39 | N78: ""y
A79: board | B79: b/ɔ/r/d/ | C79: "/ɪə/r/jə////////// | D79: "ierrrj | E79: THINGS | F79: 78 | H79: =B79 -> b/ɔ/r/d/ | N79: """"
A80: boat | B80: b/o/ʊ/t/ | C80: jə//jʊə/ʤ////////// | D80: juredi | E80: THINGS | F80: 79 | H80: =B80 -> b/o/ʊ/t/ | L80: =L78+1 -> 40 | N80: n""
A81: body | B81: b/ɑ/d/i/ | C81: "/ɪə/"/"////////// | D81: "ier"" | E81: THINGS | F81: 80 | H81: =B81 -> b/ɑ/d/i/ | N81: j""ho
A82: boil | B82: b/ɔɪ/l/ | C82: k/ə/"/////////// | D82: cher" | E82: QUALITIES | F82: 81 | H82: =B82 -> b/ɔɪ/l/ | L82: =L80+1 -> 41 | N82: veaist
A83: bone | B83: b/o/ʊ/n/ | C83: b//u/jə////////// | D83: "oeui | E83: THINGS | F83: 82 | H83: =B83 -> b/o/ʊ/n/ | N83: ""x
A84: book | B84: b/ʊ/k/ | C84: θ/"/"/////////// | D84: th"" | E84: THINGS | F84: 83 | H84: =B84 -> b/ʊ/k/ | L84: =L82+1 -> 42 | N84: "our"
A85: boot | B85: b/u/t/ | C85: r/"/"/////////// | D85: rr"" | E85: THINGS | F85: 84 | H85: =B85 -> b/u/t/ | N85: "oirh
A86: bottle | B86: b/ɑ/t/ə/l/ | C86: "/"/"/ɪə/ʤ///////// | D86: """eredi | E86: THINGS | F86: 85 | H86: =B86 -> b/ɑ/t/ə/l/ | L86: =L84+1 -> 43 | N86: "eer"""
A87: box | B87: b/ɑ/k/s/ | C87: θ/ʌ/"/"////////// | D87: tho"" | E87: THINGS | F87: 86 | H87: =B87 -> b/ɑ/k/s/ | N87: ff""th
A88: boy | B88: b/ɔɪ/ | C88: "/"//////////// | D88: "" | E88: THINGS | F88: 87 | H88: =B88 -> b/ɔɪ/ | L88: =L86+1 -> 44 | N88: ph"
A89: brain | B89: b/r/eɪ/n/ | C89: "/r/"/ʧ////////// | D89: """ch | E89: THINGS | F89: 88 | H89: =B89 -> b/r/eɪ/n/ | N89: ""oitch
A90: brake | B90: b/r/eɪ/k/ | C90: "/"/ɪə/"////////// | D90: ""ier" | E90: THINGS | F90: 89 | H90: =B90 -> b/r/eɪ/k/ | L90: =L88+1 -> 45 | N90: mm"ui"
A91: branch | B91: b/r/æ/n/ʧ/ | C91: "/"/"/"/ʤ///////// | D91: """"ge | E91: THINGS | F91: 90 | H91: =B91 -> b/r/æ/n/ʧ/ | N91: ""i"x
A92: brass | B92: b/r/æ/s/ | C92: "/"/"/θ////////// | D92: """th | E92: THINGS | F92: 91 | H92: =B92 -> b/r/æ/s/ | L92: =L90+1 -> 46 | N92: "wr""
A93: bread | B93: b/r/ɛ/d/ | C93: "/"/"/"////////// | D93: """" | E93: THINGS | F93: 92 | H93: =B93 -> b/r/ɛ/d/ | N93: ""ouy"
A94: breath | B94: b/r/ɛ/θ/ | C94: "/r/"/ŋ////////// | D94: "rh"ngue | E94: THINGS | F94: 93 | H94: =B94 -> b/r/ɛ/θ/ | L94: =L92+1 -> 47 | N94: ph"is"
A95: brick | B95: b/r/ɪ/k/ | C95: t/l/aɪ/"////////// | D95: tllie" | E95: THINGS | F95: 94 | H95: =B95 -> b/r/ɪ/k/ | N95: """"
A96: bridge | B96: b/r/ɪ/ʤ/ | C96: "/"/aʊ/"////////// | D96: ""ow" | E96: THINGS | F96: 95 | H96: =B96 -> b/r/ɪ/ʤ/ | L96: =L94+1 -> 48 | N96: ft""si
A97: bright | B97: b/r/aɪ/t/ | C97: "/θ/i/f////////// | D97: "theef | E97: QUALITIES | F97: 96 | H97: =B97 -> b/r/aɪ/t/ | N97: "zaighth
A98: broken | B98: b/r/o/ʊ/k/ə/n/ | C98: v/ʤ//ʌ/"/jʊə/h/////// | D98: vejoo"urewh | E98: QUALITIES | F98: 97 | H98: =B98 -> b/r/o/ʊ/k/ə/n/ | L98: =L96+1 -> 49 | N98: """"un
A99: brother | B99: b/r/ʌ/ð/ə/r/ | C99: "/r/ɜ/"/jʊə/r//////// | D99: "wrer"urerr | E99: THINGS | F99: 98 | H99: =B99 -> b/r/ʌ/ð/ə/r/ | N99: "di"thou"
A100: brown | B100: b/r/aʊ/n/ | C100: "/r/əʊ/r////////// | D100: "rowrr | E100: QUALITIES | F100: 99 | H100: =B100 -> b/r/aʊ/n/ | L100: =L98+1 -> 50 | N100: ""uysi
...

Sheet Verse-True
A1: 793 | F1: 1 | G1: 2 | H1: 3 | I1: 4 | J1: 5 | K1: 6 | L1: 7 | M1: 8 | N1: 9 | O1: 10 | P1: 11 | Q1: 12 | R1: 13 | S1: 14 | U1: =A1+1 -> 794 | Z1: 1 | AA1: 2 | AB1: 3 | AC1: 4 | AD1: 5 | AE1: 6 | AF1: 7 | AG1: 8 | AH1: 9 | AI1: 10 | AJ1: 11 | AK1: 12 | AL1: 13 | AM1: 14
A2: {=INDEX('All Words All Languages'!$A$2:$A$853,'Verse-True'!A1)} -> verse | B2: 1 | C2: =IF(B2<=A8,RANDBETWEEN(A4/(3/2),A4*(3/2)),"") -> 1 | D2: OG Pronunciation | E2: {=INDEX('All Words All Languages'!$H$2:$H$853,A1)} -> v/ɜ/r/s/ | F2: {=_xlfn.TEXTSPLIT(E2,"/")} -> v | G2: ɜ | H2: r | I2: s | U2: {=INDEX('All Words All Languages'!$A$2:$A$853,'Verse-True'!U1)} -> very | V2: 1 | W2: =IF(V2<=U8,RANDBETWEEN(U4/(3/2),U4*(3/2)),"") -> 1 | X2: OG Pronunciation | Y2: {=INDEX('All Words All Languages'!$H$2:$H$853,U1)} -> v/ɛ/r/i/ | Z2: {=_xlfn.TEXTSPLIT(Y2,"/")} -> v | AA2: ɛ | AB2: r | AC2: i
B3: 2 | C3: =IF(B3<=A8,RANDBETWEEN(A4/(3/2),A4*(3/2))+C2,"") -> 2 | F3: =MATCH(F2,'Language Rules Can Change'!$A$3:$A$47,0) -> 6 | G3: =MATCH(G2,'Language Rules Can Change'!$A$3:$A$47,0) -> 37 | H3: =MATCH(H2,'Language Rules Can Change'!$A$3:$A$47,0) -> 16 | I3: =MATCH(I2,'Language Rules Can Change'!$A$3:$A$47,0) -> 10 | J3: =MATCH(J2,'Language Rules Can Change'!$A$3:$A$47,0) -> #N/A | K3: =MATCH(K2,'Language Rules Can Change'!$A$3:$A$47,0) -> #N/A | L3: =MATCH(L2,'Language Rules Can Change'!$A$3:$A$47,0) -> #N/A | M3: =MATCH(M2,'Language Rules Can Change'!$A$3:$A$47,0) -> #N/A | ... S3: =MATCH(S2,'Language Rules Can Change'!$A$3:$A$47,0) -> #N/A | V3: 2 | W3: =IF(V3<=U8,RANDBETWEEN(U4/(3/2),U4*(3/2))+W2,"") -> 2 | Z3: =MATCH(Z2,'Language Rules Can Change'!$A$3:$A$47,0) -> 6 | AA3: =MATCH(AA2,'Language Rules Can Change'!$A$3:$A$47,0) -> 26 | AB3: =MATCH(AB2,'Language Rules Can Change'!$A$3:$A$47,0) -> 16 | AC3: =MATCH(AC2,'Language Rules Can Change'!$A$3:$A$47,0) -> 32 | AD3: =MATCH(AD2,'Language Rules Can Change'!$A$3:$A$47,0) -> #N/A | AE3: =MATCH(AE2,'Language Rules Can Change'!$A$3:$A$47,0) -> #N/A | AF3: =MATCH(AF2,'Language Rules Can Change'!$A$3:$A$47,0) -> #N/A | AG3: =MATCH(AG2,'Language Rules Can Change'!$A$3:$A$47,0) -> #N/A | ... AM3: =MATCH(AM2,'Language Rules Can Change'!$A$3:$A$47,0) -> #N/A
A4: ='All Words All Languages'!$I$1 -> 1 | B4: 3 | C4: =IF(B4<=A8,RANDBETWEEN(A4/(3/2),A4*(3/2))+C3,"") -> 3 | F4: =RAND() -> 0.15725068 | G4: =RAND() -> 0.84206995 | H4: =RAND() -> 0.25653096 | I4: =RAND() -> 0.37832126 | J4: =RAND() -> 0.68020431 | K4: =RAND() -> 0.80189063 | L4: =RAND() -> 0.78581185 | M4: =RAND() -> 0.43275442 | ... S4: =RAND() -> 0.26594858 | U4: ='All Words All Languages'!$I$1 -> 1 | V4: 3 | W4: =IF(V4<=U8,RANDBETWEEN(U4/(3/2),U4*(3/2))+W3,"") -> 3 | Z4: =RAND() -> 0.42056188 | AA4: =RAND() -> 0.075480408 | AB4: =RAND() -> 0.046872468 | AC4: =RAND() -> 0.81258163 | AD4: =RAND() -> 0.64415259 | AE4: =RAND() -> 0.41144904 | AF4: =RAND() -> 0.86563589 | AG4: =RAND() -> 0.59159676 | ... AM4: =RAND() -> 0.89490282
